Workbook
Name CategoryList: #REF!

Sheet Transactions
A1: Date | B1: Description | C1: Type (IN/OUT) | D1: Amount (Excl. VAT) | E1: Account | F1: Category | G1: Project | H1: Material Item | I1: Qty | J1: Rate | K1: Party Name | L1: Party Type | M1: Invoice # | N1: Tax % | O1: Tax Amount | P1: Total Amount | Q1: Payment Status | R1: Notes
A2: 45965 | B2: chemicals | C2: OUT | D2: 220 | E2: Cash | F2: Material Purchase | G2: SS316 Pipeline Work | H2: Material/Tools | K2: TBD | L2: Supplier | N2: 15 | O2: =IF(OR(D2="", N2=""), "", ROUND(D2 * N2 / 100, 2)) -> 33 | P2: =IF(D2="", "", D2 + O2) -> 253 | Q2: Paid
A3: 45965 | B3: Chemicals | C3: OUT | D3: 169.5 | E3: Cash | F3: Material Purchase | G3: SS316 Pipeline Work | H3: Material/Tools | K3: TBD | L3: Supplier | N3: 15 | O3: =IF(OR(D3="", N3=""), "", ROUND(D3 * N3 / 100, 2)) -> 25.43 | P3: =IF(D3="", "", D3 + O3) -> 194.93 | Q3: Paid
A4: 45965 | B4: SS316 albo | C4: OUT | D4: 269.57 | E4: Cash | F4: Material Purchase | G4: SS316 Pipeline Work | H4: Material/Tools | K4: TBD | L4: Supplier | N4: 15 | O4: =IF(OR(D4="", N4=""), "", ROUND(D4 * N4 / 100, 2)) -> 40.44 | P4: =IF(D4="", "", D4 + O4) -> 310.01 | Q4: Paid
A5: 45965 | B5: SS316 plastic raw material | C5: OUT | D5: 473.91 | E5: Cash | F5: Material Purchase | G5: SS316 Pipeline Work | H5: Material/Tools | K5: TBD | L5: Supplier | N5: 15 | O5: =IF(OR(D5="", N5=""), "", ROUND(D5 * N5 / 100, 2)) -> 71.09 | P5: =IF(D5="", "", D5 + O5) -> 545 | Q5: Paid
A6: 45966 | B6: Welding machine | C6: OUT | D6: 1808.7 | E6: Cash | F6: Equipment Purchase | G6: SS316 Pipeline Work | H6: Material/Tools | K6: TBD | L6: Supplier | N6: 15 | O6: =IF(OR(D6="", N6=""), "", ROUND(D6 * N6 / 100, 2)) -> 271.31 | P6: =IF(D6="", "", D6 + O6) -> 2080.01 | Q6: Paid
A7: 45966 | B7: Food for team | C7: OUT | D7: 217.39 | E7: Cash | F7: Food Expense | G7: SS316 Pipeline Work | H7: Food for Team | K7: TBD | L7: Supplier | N7: 15 | O7: =IF(OR(D7="", N7=""), "", ROUND(D7 * N7 / 100, 2)) -> 32.61 | P7: =IF(D7="", "", D7 + O7) -> 250 | Q7: Paid
A8: 45966 | B8: Labour charges 2 days | C8: OUT | D8: 886.96 | E8: Cash | F8: Labour Expense | G8: SS316 Pipeline Work | H8: Labour Chares | K8: TBD | L8: Supplier | N8: 15 | O8: =IF(OR(D8="", N8=""), "", ROUND(D8 * N8 / 100, 2)) -> 133.04 | P8: =IF(D8="", "", D8 + O8) -> 1020 | Q8: Paid
A9: 45966 | B9: Petrol for project | C9: OUT | D9: 301.74 | E9: Cash | F9: Fuel Expense | G9: SS316 Pipeline Work | H9: Fuel Expense | K9: TBD | L9: Supplier | N9: 15 | O9: =IF(OR(D9="", N9=""), "", ROUND(D9 * N9 / 100, 2)) -> 45.26 | P9: =IF(D9="", "", D9 + O9) -> 347 | Q9: Paid
A10: 45966 | B10: SS316 pipes 18m | C10: OUT | D10: 434.78 | E10: Cash | F10: Material Purchase | G10: SS316 Pipeline Work | H10: Material/Tools | K10: TBD | L10: Supplier | N10: 15 | O10: =IF(OR(D10="", N10=""), "", ROUND(D10 * N10 / 100, 2)) -> 65.22 | P10: =IF(D10="", "", D10 + O10) -> 500 | Q10: Paid
A11: 45966 | B11: Invoice raised for SS316 Pipeline Work | C11: IN | D11: 4000 | E11: Cash | F11: Project Income | G11: SS316 Pipeline Work | H11: N/A | K11: Oud Lover Factory | L11: Client | M11: INV/2025/00041 | N11: 15 | O11: =IF(OR(D11="", N11=""), "", ROUND(D11 * N11 / 100, 2)) -> 600 | P11: =IF(D11="", "", D11 + O11) -> 4600 | Q11: Paid | R11: 100% Payment Received
A12: 45967 | B12: Invoice Raised for Instlattion of Sign Board | C12: IN | D12: 2000 | E12: Cash | F12: Project Income | G12: Instalation of Sign Board | H12: N/A | I12: 1 | K12: Feedco Investment Company | L12: Client | M12: INV/2025/00044 | N12: 15 | O12: =IF(OR(D12="", N12=""), "", ROUND(D12 * N12 / 100, 2)) -> 300 | P12: =IF(D12="", "", D12 + O12) -> 2300 | Q12: Paid | R12: 100% Payment Received
A13: 45967 | B13: Net/Bolts | C13: OUT | D13: 104.35 | E13: Cash | F13: Material Purchase | G13: Instalation of Sign Board | H13: Material/Tools | K13: TBD | L13: Supplier | N13: 15 | O13: =IF(OR(D13="", N13=""), "", ROUND(D13 * N13 / 100, 2)) -> 15.65 | P13: =IF(D13="", "", D13 + O13) -> 120 | Q13: Paid
A14: 45967 | B14: Drill Machine | C14: OUT | D14: 417.39 | E14: Cash | F14: Equipment Purchase | G14: Instalation of Sign Board | H14: Material/Tools | K14: TBD | L14: Supplier | N14: 15 | O14: =IF(OR(D14="", N14=""), "", ROUND(D14 * N14 / 100, 2)) -> 62.61 | P14: =IF(D14="", "", D14 + O14) -> 480 | Q14: Paid
A15: 45967 | B15: Food for team | C15: OUT | D15: 139.13 | E15: Cash | F15: Food Expense | G15: Instalation of Sign Board | H15: Food for Team | K15: TBD | L15: Supplier | N15: 15 | O15: =IF(OR(D15="", N15=""), "", ROUND(D15 * N15 / 100, 2)) -> 20.87 | P15: =IF(D15="", "", D15 + O15) -> 160 | Q15: Paid
A16: 45967 | B16: Petrol for project | C16: OUT | D16: 113.04 | E16: Cash | F16: Fuel Expense | G16: Instalation of Sign Board | H16: Fuel Expense | K16: TBD | L16: Supplier | N16: 15 | O16: =IF(OR(D16="", N16=""), "", ROUND(D16 * N16 / 100, 2)) -> 16.96 | P16: =IF(D16="", "", D16 + O16) -> 130 | Q16: Paid
A17: 45970 | B17: 50% advance receive (net only/no VAT) | C17: IN | D17: 7425 | E17: Cash | F17: Project Income | G17: Fabrication of Steel Ramp | H17: N/A | I17: 1 | K17: Bahri Logistics | L17: Client | N17: 0 | O17: =IF(OR(D17="", N17=""), "", ROUND(D17 * N17 / 100, 2)) -> 0 | P17: =IF(D17="", "", D17 + O17) -> 7425 | Q17: Partially Paid | R17: only Project Advance, 50% received, (VAT 100% pending)
A18: 45971 | B18: Industrial lights & bolts | C18: OUT | D18: 170.43 | E18: Cash | F18: Equipment Purchase | G18: Fabrication of Steel Ramp | H18: Material/Tools | K18: TBD | L18: Supplier | N18: 15 | O18: =IF(OR(D18="", N18=""), "", ROUND(D18 * N18 / 100, 2)) -> 25.56 | P18: =IF(D18="", "", D18 + O18) -> 195.99 | Q18: Paid
A19: 45971 | B19: Steel material | C19: OUT | D19: 170.43 | E19: Cash | F19: Material Purchase | G19: Fabrication of Steel Ramp | H19: Material/Tools | K19: TBD | L19: Supplier | N19: 15 | O19: =IF(OR(D19="", N19=""), "", ROUND(D19 * N19 / 100, 2)) -> 25.56 | P19: =IF(D19="", "", D19 + O19) -> 195.99 | Q19: Paid
A20: 45972 | B20: Steel sheet 4mm*6m | C20: OUT | D20: 1095.65 | E20: Cash | F20: Material Purchase | G20: Fabrication of Steel Ramp | H20: Material/Tools | K20: TBD | L20: Supplier | N20: 15 | O20: =IF(OR(D20="", N20=""), "", ROUND(D20 * N20 / 100, 2)) -> 164.35 | P20: =IF(D20="", "", D20 + O20) -> 1260 | Q20: Paid
A21: 45972 | B21: Crane transport | C21: OUT | D21: 695.65 | E21: Cash | F21: Transport Expense | G21: Fabrication of Steel Ramp | H21: Transport | K21: TBD | L21: Supplier | N21: 15 | O21: =IF(OR(D21="", N21=""), "", ROUND(D21 * N21 / 100, 2)) -> 104.35 | P21: =IF(D21="", "", D21 + O21) -> 800 | Q21: Paid
A22: 45973 | B22: Chenku sheet | C22: OUT | D22: 1078.26 | E22: Cash | F22: Material Purchase | G22: Fabrication of Steel Ramp | H22: Material/Tools | K22: TBD | L22: Supplier | N22: 15 | O22: =IF(OR(D22="", N22=""), "", ROUND(D22 * N22 / 100, 2)) -> 161.74 | P22: =IF(D22="", "", D22 + O22) -> 1240 | Q22: Paid
A23: 45973 | B23: Welding rods / grinding / paint | C23: OUT | D23: 330.43 | E23: Cash | F23: Equipment Purchase | G23: Fabrication of Steel Ramp | H23: Material/Tools | K23: TBD | L23: Supplier | N23: 15 | O23: =IF(OR(D23="", N23=""), "", ROUND(D23 * N23 / 100, 2)) -> 49.56 | P23: =IF(D23="", "", D23 + O23) -> 379.99 | Q23: Paid
A24: 45974 | B24: Food for team | C24: OUT | D24: 434.78 | E24: Cash | F24: Food Expense | G24: Fabrication of Steel Ramp | H24: Food for Team | K24: TBD | L24: Supplier | N24: 15 | O24: =IF(OR(D24="", N24=""), "", ROUND(D24 * N24 / 100, 2)) -> 65.22 | P24: =IF(D24="", "", D24 + O24) -> 500 | Q24: Paid
A25: 45974 | B25: Labour charges of 5 Days | C25: OUT | D25: 2078.26 | E25: Cash | F25: Labour Expense | G25: Fabrication of Steel Ramp | H25: Labour Chares | K25: Mr shahid | L25: Supplier | N25: 15 | O25: =IF(OR(D25="", N25=""), "", ROUND(D25 * N25 / 100, 2)) -> 311.74 | P25: =IF(D25="", "", D25 + O25) -> 2390 | Q25: Paid
A26: 45975 | B26: Petrol for project | C26: OUT | D26: 173.91 | E26: Cash | F26: Fuel Expense | G26: Fabrication of Steel Ramp | H26: Fuel Expense | K26: TBD | L26: Supplier | N26: 15 | O26: =IF(OR(D26="", N26=""), "", ROUND(D26 * N26 / 100, 2)) -> 26.09 | P26: =IF(D26="", "", D26 + O26) -> 200 | Q26: Paid
A27: 45976 | B27: Invoice raised for Fabrication of Steel Ramp | C27: IN | D27: 7425 | E27: Accounts Receivable | F27: Project Income | G27: Fabrication of Steel Ramp | H27: N/A | I27: 1 | K27: Bahri Logistics | L27: Client | M27: INV/2025/00051 | N27: 0 | O27: =IF(OR(D27="", N27=""), "", ROUND(D27 * N27 / 100, 2)) -> 0 | P27: =IF(D27="", "", D27 + O27) -> 7425 | Q27: Credit | R27: 50% final amount is pending
A28: 45976 | B28: Same Invoice raised for Tax Collection | C28: IN | D28: 2227.5 | E28: Accounts Receivable | F28: Project Income | G28: Fabrication of Steel Ramp | H28: N/A | K28: Bahri Logistics | L28: Client | M28: INV/2025/00051 | N28: 0 | O28: =IF(OR(D28="", N28=""), "", ROUND(D28 * N28 / 100, 2)) -> 0 | P28: =IF(D28="", "", D28 + O28) -> 2227.5 | Q28: Credit | R28: 100% VAT amount is pending
A29: 45981 | B29: 100% payment received | C29: IN | D29: 27000 | E29: Cash | F29: Project Income | G29: Fabrication of SS+Steel Pillows | H29: N/A | I29: 10 pcs | K29: Fosam Company Limited | L29: Client | N29: 15 | O29: =IF(OR(D29="", N29=""), "", ROUND(D29 * N29 / 100, 2)) -> 4050 | P29: =IF(D29="", "", D29 + O29) -> 31050 | Q29: Paid | R29: 100% Paymment Received Before starting the Project
A30: 45987 | B30: SIDUR sheet 8mm*1.5m/3m | C30: OUT | D30: 2543.48 | E30: Cash | F30: Material Purchase | G30: Fabrication of SS+Steel Pillows | H30: Material/Tools | K30: Alnafie Steel | L30: Supplier | N30: 15 | O30: =IF(OR(D30="", N30=""), "", ROUND(D30 * N30 / 100, 2)) -> 381.52 | P30: =IF(D30="", "", D30 + O30) -> 2925 | Q30: Paid
A31: 45987 | B31: Lathe Expense | C31: OUT | D31: 1200 | E31: Accounts Payable | F31: Repair & Maintenance Expense | G31: Fabrication of SS+Steel Pillows | H31: Material/Tools | K31: Arif bangali | L31: Supplier | N31: 0 | O31: =IF(OR(D31="", N31=""), "", ROUND(D31 * N31 / 100, 2)) -> 0 | P31: =IF(D31="", "", D31 + O31) -> 1200 | Q31: Credit | R31: Credit Payment for Lathe Work
A32: 45987 | B32: Transport | C32: OUT | D32: 217.39 | E32: Cash | F32: Transport Expense | G32: Fabrication of SS+Steel Pillows | H32: Transport | K32: TBD | L32: Supplier | N32: 15 | O32: =IF(OR(D32="", N32=""), "", ROUND(D32 * N32 / 100, 2)) -> 32.61 | P32: =IF(D32="", "", D32 + O32) -> 250 | Q32: Paid
A33: 45987 | B33: Rolling of SIDUR sheet | C33: OUT | D33: 695.65 | E33: Cash | F33: Material Purchase | G33: Fabrication of SS+Steel Pillows | H33: Material/Tools | K33: MZY Steel | L33: Supplier | N33: 15 | O33: =IF(OR(D33="", N33=""), "", ROUND(D33 * N33 / 100, 2)) -> 104.35 | P33: =IF(D33="", "", D33 + O33) -> 800 | Q33: Paid
A34: 45988 | B34: Welding rods / grinding / paint | C34: OUT | D34: 591.3 | E34: Cash | F34: Equipment Purchase | G34: Fabrication of SS+Steel Pillows | H34: Material/Tools | K34: Baity BTC | L34: Supplier | N34: 15 | O34: =IF(OR(D34="", N34=""), "", ROUND(D34 * N34 / 100, 2)) -> 88.7 | P34: =IF(D34="", "", D34 + O34) -> 680 | Q34: Paid
A35: 45988 | B35: labour charges of 3 days | C35: OUT | D35: 1417.39 | E35: Cash | F35: Labour Expense | G35: Fabrication of SS+Steel Pillows | H35: Material/Tools | K35: Mr shahid | L35: Supplier | N35: 15 | O35: =IF(OR(D35="", N35=""), "", ROUND(D35 * N35 / 100, 2)) -> 212.61 | P35: =IF(D35="", "", D35 + O35) -> 1630 | Q35: Paid
A36: 45988 | B36: Commission | C36: OUT | D36: 4000 | E36: Cash | F36: Commission Paid | G36: Fabrication of SS+Steel Pillows | H36: Commission Paid | K36: fosam agent | L36: Supplier | N36: 0 | O36: =IF(OR(D36="", N36=""), "", ROUND(D36 * N36 / 100, 2)) -> 0 | P36: =IF(D36="", "", D36 + O36) -> 4000 | Q36: Paid | R36: Commission given to Mr Halwani
A37: 45988 | B37: Petrol for project | C37: OUT | D37: 60.87 | E37: Cash | F37: Fuel Expense | G37: Fabrication of SS+Steel Pillows | H37: Fuel Expense | K37: TBD | L37: Supplier | N37: 15 | O37: =IF(OR(D37="", N37=""), "", ROUND(D37 * N37 / 100, 2)) -> 9.13 | P37: =IF(D37="", "", D37 + O37) -> 70 | Q37: Paid
A38: 45988 | B38: Food for team | C38: OUT | D38: 295.65 | E38: Cash | F38: Food Expense | G38: Fabrication of SS+Steel Pillows | H38: Food for Team | K38: TBD | L38: Supplier | N38: 15 | O38: =IF(OR(D38="", N38=""), "", ROUND(D38 * N38 / 100, 2)) -> 44.35 | P38: =IF(D38="", "", D38 + O38) -> 340 | Q38: Paid
A39: 45988 | B39: Steel material | C39: OUT | D39: 434.78 | E39: Cash | F39: Material Purchase | G39: Fabrication of SS+Steel Pillows | H39: Material/Tools | K39: TBD | L39: Supplier | N39: 15 | O39: =IF(OR(D39="", N39=""), "", ROUND(D39 * N39 / 100, 2)) -> 65.22 | P39: =IF(D39="", "", D39 + O39) -> 500 | Q39: Paid
A40: 45989 | B40: Electricity bills paid of work shop+Tariq commission | C40: OUT | D40: 900 | E40: Cash | F40: Electricity Expense | H40: Workshop Electricity bill | K40: Tariq Yamni workshop | L40: Supplier | N40: 0 | O40: =IF(OR(D40="", N40=""), "", ROUND(D40 * N40 / 100, 2)) -> 0 | P40: =IF(D40="", "", D40 + O40) -> 900 | Q40: Paid | R40: Company General Expense
A41: 45989 | B41: Labour Charges for previous Project | C41: OUT | D41: 3000 | E41: Cash | F41: Labour Expense | H41: Labour Chares | K41: Mr shahid | L41: Supplier | N41: 0 | O41: =IF(OR(D41="", N41=""), "", ROUND(D41 * N41 / 100, 2)) -> 0 | P41: =IF(D41="", "", D41 + O41) -> 3000 | Q41: Paid | R41: Company General Expense
A42: 45989 | B42: Loader+Hotel Bill | C42: OUT | D42: 590 | E42: Cash | F42: Transport Expense | H42: Transport+Food for Team | K42: Naeem+Tahir | L42: Supplier | N42: 0 | O42: =IF(OR(D42="", N42=""), "", ROUND(D42 * N42 / 100, 2)) -> 0 | P42: =IF(D42="", "", D42 + O42) -> 590 | Q42: Paid | R42: Company General Expense
A43: 45989 | B43: Payment Transfer | C43: OUT | D43: 500 | E43: Cash | F43: Settlement | H43: Loan Paid | K43: Abdullah | L43: Supplier | N43: 0 | O43: =IF(OR(D43="", N43=""), "", ROUND(D43 * N43 / 100, 2)) -> 0 | P43: =IF(D43="", "", D43 + O43) -> 500 | Q43: Paid | R43: Company General Expense
A44: 45989 | B44: Refilling of Gas+Oxygen Cylinder | C44: OUT | D44: 75 | E44: Cash | F44: Equipment Purchase | H44: Material/Tools | K44: TBD | L44: Supplier | N44: 0 | O44: =IF(OR(D44="", N44=""), "", ROUND(D44 * N44 / 100, 2)) -> 0 | P44: =IF(D44="", "", D44 + O44) -> 75 | Q44: Paid | R44: Company General Expense
A45: 45989 | B45: Purchasing of Cement+Clay+Concrete+Bolts | C45: OUT | D45: 119.13 | E45: Cash | F45: Equipment Purchase | H45: Material/Tools | K45: Al Riyadh Center | L45: Supplier | N45: 15 | O45: =IF(OR(D45="", N45=""), "", ROUND(D45 * N45 / 100, 2)) -> 17.87 | P45: =IF(D45="", "", D45 + O45) -> 137 | Q45: Paid | R45: Company General Expense
A46: 45989 | B46: Fuel Expense | C46: OUT | D46: 60.87 | E46: Cash | F46: Fuel Expense | H46: Fuel Expense | K46: Fuel Pump | L46: Supplier | N46: 15 | O46: =IF(OR(D46="", N46=""), "", ROUND(D46 * N46 / 100, 2)) -> 9.13 | P46: =IF(D46="", "", D46 + O46) -> 70 | Q46: Paid | R46: Company General Expense
A47: 45989 | B47: Level of Concrete | C47: OUT | D47: 10 | E47: Cash | F47: Equipment Purchase | H47: Material/Tools | K47: Al Riyadh Center | L47: Supplier | N47: 0 | O47: =IF(OR(D47="", N47=""), "", ROUND(D47 * N47 / 100, 2)) -> 0 | P47: =IF(D47="", "", D47 + O47) -> 10 | Q47: Paid | R47: Company General Expense
A48: 45989 | B48: Car Battery Purchase for Yaris | C48: OUT | D48: 156.52 | E48: Cash | F48: Equipment Purchase | H48: Material/Tools | K48: TBD | L48: Supplier | N48: 15 | O48: =IF(OR(D48="", N48=""), "", ROUND(D48 * N48 / 100, 2)) -> 23.48 | P48: =IF(D48="", "", D48 + O48) -> 180 | Q48: Paid | R48: Company General Expense
A49: 45989 | B49: Payment Transfer | C49: OUT | D49: 600 | E49: Cash | F49: Settlement | H49: Other | K49: Yasir Shah | L49: Employee | N49: 0 | O49: =IF(OR(D49="", N49=""), "", ROUND(D49 * N49 / 100, 2)) -> 0 | P49: =IF(D49="", "", D49 + O49) -> 600 | Q49: Paid | R49: Advance to Employee
A50: 45989 | B50: Bearing Purchase | C50: OUT | D50: 1434.79 | E50: Accounts Payable | F50: Material Purchase | H50: TBD | K50: TBD | L50: Supplier | N50: 15 | O50: =IF(OR(D50="", N50=""), "", ROUND(D50 * N50 / 100, 2)) -> 215.22 | P50: =IF(D50="", "", D50 + O50) -> 1650.01 | Q50: Credit | R50: Credit Purchase (Supplier Due)
A51: 45989 | B51: Company CR updated | C51: OUT | D51: 1700 | E51: Accounts Payable | F51: Company Office Expense | H51: CR updated | K51: TBD | L51: Supplier | N51: 0 | O51: =IF(OR(D51="", N51=""), "", ROUND(D51 * N51 / 100, 2)) -> 0 | P51: =IF(D51="", "", D51 + O51) -> 1700 | Q51: Credit | R51: Credit Purchase (Supplier Due)
... A54: 45990 | B54: Traffic violation fine paid on behalf of employee | C54: OUT | D54: 338 | E54: Cash | F54: Fine Paid | H54: Trafic violation Challan | K54: Yasir Shah | L54: Employee | N54: 0 | O54: =IF(OR(D54="", N54=""), "", ROUND(D54 * N54 / 100, 2)) -> 0 | P54: =IF(D54="", "", D54 + O54) -> 338 | Q54: Paid | R54: Company paid employee’s traffic fine – approved expense
A55: 45990 | B55: Gasket Purchase for Riviva Comprossor | C55: OUT | D55: 130.44 | E55: Cash | F55: Material Purchase | H55: Gaskit Red 3mm | I55: 1 | K55: Al Amal Trading Company | L55: Supplier | M55: SHA/24/16431 | N55: 15 | O55: =IF(OR(D55="", N55=""), "", ROUND(D55 * N55 / 100, 2)) -> 19.57 | P55: =IF(D55="", "", D55 + O55) -> 150.01 | Q55: Paid | R55: Material Purchase for Riviva Comprossor
A56: 45991 | B56: Net/Bolts | C56: OUT | D56: 175.9 | E56: Cash | F56: Material Purchase | H56: Net/Bolts | I56: 53 | K56: Umar saud company | L56: Supplier | M56: 50677 | N56: 15 | O56: =IF(OR(D56="", N56=""), "", ROUND(D56 * N56 / 100, 2)) -> 26.39 | P56: =IF(D56="", "", D56 + O56) -> 202.29 | Q56: Paid | R56: Company General Expense
A57: 45991 | B57: Food for team | C57: OUT | D57: 13.04 | E57: Cash | F57: Food Expense | H57: Food for Team | K57: Al Bukra | L57: Supplier | M57: 273 | N57: 15 | O57: =IF(OR(D57="", N57=""), "", ROUND(D57 * N57 / 100, 2)) -> 1.96 | P57: =IF(D57="", "", D57 + O57) -> 15 | Q57: Paid | R57: Company General Expense
A58: 45991 | B58: Fuel Expense | C58: OUT | D58: 86.9 | E58: Cash | F58: Fuel Expense | H58: Fuel Expense | K58: TBD | L58: Supplier | N58: 15 | O58: =IF(OR(D58="", N58=""), "", ROUND(D58 * N58 / 100, 2)) -> 13.04 | P58: =IF(D58="", "", D58 + O58) -> 99.94 | Q58: Paid | R58: Company General Expense
A59: 45991 | B59: Fuel for owner Car | C59: OUT | D59: 43.48 | E59: Cash | F59: Fuel Expense | H59: Fuel Expense | K59: SASSCO | L59: Supplier | M59: 329395 | N59: 15 | O59: =IF(OR(D59="", N59=""), "", ROUND(D59 * N59 / 100, 2)) -> 6.52 | P59: =IF(D59="", "", D59 + O59) -> 50 | Q59: Paid | R59: Company General Expense
A60: 45992 | B60: Food for team | C60: OUT | D60: 10.5 | E60: Cash | F60: Food Expense | H60: Food for Team | K60: TBD | L60: Supplier | N60: 0 | O60: =IF(OR(D60="", N60=""), "", ROUND(D60 * N60 / 100, 2)) -> 0 | P60: =IF(D60="", "", D60 + O60) -> 10.5 | Q60: Paid | R60: Company General Expense
A61: 45992 | B61: Fuel for owner Car | C61: OUT | D61: 30.43 | E61: Cash | F61: Fuel Expense | H61: Fuel Expense | K61: TBD | L61: Supplier | N61: 15 | O61: =IF(OR(D61="", N61=""), "", ROUND(D61 * N61 / 100, 2)) -> 4.56 | P61: =IF(D61="", "", D61 + O61) -> 34.99 | Q61: Paid | R61: Company General Expense
A62: 45992 | B62: Isolation+Grill+Square Tube 40*80m*6m | C62: OUT | D62: 836 | E62: Cash | F62: Material Purchase | G62: Fabrication of Steel Shose for Forklift | H62: Material/Tools | I62: 7 | K62: Khaled Steel | L62: Supplier | M62: 3921/3920 | N62: 15 | O62: =IF(OR(D62="", N62=""), "", ROUND(D62 * N62 / 100, 2)) -> 125.4 | P62: =IF(D62="", "", D62 + O62) -> 961.4 | Q62: Paid | R62: Project Expense
A63: 45992 | B63: Shafts | C63: OUT | D63: 260.86 | E63: Cash | F63: Material Purchase | G63: Fabrication of Steel Shose for Forklift | H63: Material/Tools | I63: 2 | K63: Al Nafie Steel | L63: Supplier | M63: JEDCash/100262 | N63: 15 | O63: =IF(OR(D63="", N63=""), "", ROUND(D63 * N63 / 100, 2)) -> 39.13 | P63: =IF(D63="", "", D63 + O63) -> 299.99 | Q63: Paid | R63: Project Expense
A64: 45992 | B64: Food for team | C64: OUT | D64: 150 | E64: Cash | F64: Food Expense | G64: Fabrication of Steel Shose for Forklift | H64: Food for Team | K64: TBD | L64: Supplier | N64: 0 | O64: =IF(OR(D64="", N64=""), "", ROUND(D64 * N64 / 100, 2)) -> 0 | P64: =IF(D64="", "", D64 + O64) -> 150 | Q64: Paid | R64: Project Expense
A65: 45992 | B65: Transport Expense | C65: OUT | D65: 100 | E65: Cash | F65: Transport Expense | G65: Fabrication of Steel Shose for Forklift | H65: Transport Expense | K65: Naeem | L65: Supplier | N65: 0 | O65: =IF(OR(D65="", N65=""), "", ROUND(D65 * N65 / 100, 2)) -> 0 | P65: =IF(D65="", "", D65 + O65) -> 100 | Q65: Paid | R65: Project Expense
A66: 45992 | B66: Owner Dinner | C66: OUT | D66: 43 | E66: Cash | F66: Food Expense | H66: Food for Team | K66: TBD | L66: Supplier | N66: 0 | O66: =IF(OR(D66="", N66=""), "", ROUND(D66 * N66 / 100, 2)) -> 0 | P66: =IF(D66="", "", D66 + O66) -> 43 | Q66: Paid | R66: Company General Expense
A67: 45992 | B67: Moblile and Petrol of Nissan Car | C67: OUT | D67: 73.9 | E67: Cash | F67: Car Maintanence Expense | H67: Moblile change and petrol | K67: TBD | L67: Supplier | N67: 15 | O67: =IF(OR(D67="", N67=""), "", ROUND(D67 * N67 / 100, 2)) -> 11.09 | P67: =IF(D67="", "", D67 + O67) -> 84.99 | Q67: Paid | R67: Company General Expense
A68: 45992 | B68: Nissan car Maintenance | C68: OUT | D68: 1300 | E68: Cash | F68: Car Maintanence Expense | H68: General Miantenece | K68: Makkah Car Center | L68: Supplier | N68: 0 | O68: =IF(OR(D68="", N68=""), "", ROUND(D68 * N68 / 100, 2)) -> 0 | P68: =IF(D68="", "", D68 + O68) -> 1300 | Q68: Paid | R68: Company General Expense
A69: 45992 | B69: invoice rasied and Payment Received | C69: IN | D69: 8800 | E69: Cash | F69: Project Income | G69: Fitting of Press Roller | H69: N/A | K69: Feedco Investment Company | L69: Client | M69: INV/2025/00057 | N69: 15 | O69: =IF(OR(D69="", N69=""), "", ROUND(D69 * N69 / 100, 2)) -> 1320 | P69: =IF(D69="", "", D69 + O69) -> 10120 | Q69: Paid | R69: 100% Payment Received
A70: 45992 | B70: Transport and dabbad Expense | C70: OUT | D70: 700 | E70: Cash | F70: Transport Expense | G70: Fitting of Press Roller | H70: Transport Expense | K70: TBD | L70: Supplier | N70: 0 | O70: =IF(OR(D70="", N70=""), "", ROUND(D70 * N70 / 100, 2)) -> 0 | P70: =IF(D70="", "", D70 + O70) -> 700 | Q70: Paid | R70: Project Expense
A71: 45992 | B71: Bangali Workshop Expense | C71: OUT | D71: 3750 | E71: Cash | F71: Repair & Maintenance Expense | G71: Fitting of Press Roller | H71: Material/Tools | K71: Arif bangali | L71: Supplier | N71: 0 | O71: =IF(OR(D71="", N71=""), "", ROUND(D71 * N71 / 100, 2)) -> 0 | P71: =IF(D71="", "", D71 + O71) -> 3750 | Q71: Paid | R71: Project Expense
A72: 45993 | B72: Fuel Expanse for Nissan | C72: OUT | D72: 70.4 | E72: Cash | F72: Fuel Expense | H72: Fuel Expense | K72: TBD | L72: Supplier | N72: 15 | O72: =IF(OR(D72="", N72=""), "", ROUND(D72 * N72 / 100, 2)) -> 10.56 | P72: =IF(D72="", "", D72 + O72) -> 80.96 | Q72: Paid | R72: Company General Expense
A73: 45993 | B73: Paymnet Received of Epoxy Projet | C73: IN | D73: 15000 | E73: Cash | F73: Project Income | G73: Epoxy Paint Project Jazzan | H73: N/A | K73: Company Rosomat/Wasim | L73: Client | M73: INV/2026/00024 | N73: 0 | O73: =IF(OR(D73="", N73=""), "", ROUND(D73 * N73 / 100, 2)) -> 0 | P73: =IF(D73="", "", D73 + O73) -> 15000 | Q73: Paid | R73: 50% Payment Receive without VAT
A74: 45993 | B74: Epoxy project Purchasing | C74: OUT | D74: 7691.3 | E74: Cash | F74: Material Purchase | G74: Epoxy Paint Project Jazzan | H74: Paints and others | K74: TBD | L74: Supplier | N74: 15 | O74: =IF(OR(D74="", N74=""), "", ROUND(D74 * N74 / 100, 2)) -> 1153.7 | P74: =IF(D74="", "", D74 + O74) -> 8845 | Q74: Paid | R74: Project expense
A75: 45993 | B75: Labour Charges in Advance for Epoxy Paint Project | C75: OUT | D75: 3000 | E75: Cash | F75: Labour Expense | G75: Epoxy Paint Project Jazzan | H75: Labour Charges | K75: Muhammad | L75: Supplier | N75: 0 | O75: =IF(OR(D75="", N75=""), "", ROUND(D75 * N75 / 100, 2)) -> 0 | P75: =IF(D75="", "", D75 + O75) -> 3000 | Q75: Paid | R75: Project Expense
A76: 45994 | B76: other expense of Epoxy paint project | C76: OUT | D76: 500 | E76: Cash | F76: Material Purchase | G76: Epoxy Paint Project Jazzan | H76: Other | K76: TBD | L76: Supplier | N76: 0 | O76: =IF(OR(D76="", N76=""), "", ROUND(D76 * N76 / 100, 2)) -> 0 | P76: =IF(D76="", "", D76 + O76) -> 500 | Q76: Paid | R76: Project Expense
A77: 45994 | B77: Payment received of Loader Project | C77: IN | D77: 5000 | E77: Cash | F77: Project Income | G77: Maintenance of Loader | H77: N/A | K77: Sapac Company | L77: Client | M77: INV/2025/00026 | N77: 15 | O77: =IF(OR(D77="", N77=""), "", ROUND(D77 * N77 / 100, 2)) -> 750 | P77: =IF(D77="", "", D77 + O77) -> 5750 | Q77: Paid | R77: 100% Paymnet Received
A78: 45994 | B78: Seals Purchase | C78: OUT | D78: 1150 | E78: Cash | F78: Material Purchase | G78: Maintenance of Loader | H78: Material/Tools | K78: TBD | L78: Supplier | N78: 0 | O78: =IF(OR(D78="", N78=""), "", ROUND(D78 * N78 / 100, 2)) -> 0 | P78: =IF(D78="", "", D78 + O78) -> 1150 | Q78: Paid | R78: Project Expense
A79: 45994 | B79: Bangali Workshop Expense | C79: OUT | D79: 1400 | E79: Accounts Payable | F79: Repair & Maintenance Expense | G79: Maintenance of Loader | H79: Material/Tools | K79: Arif bangali | L79: Supplier | N79: 0 | O79: =IF(OR(D79="", N79=""), "", ROUND(D79 * N79 / 100, 2)) -> 0 | P79: =IF(D79="", "", D79 + O79) -> 1400 | Q79: Credit | R79: Payment pending on company of this project
A80: 45994 | B80: Owner Withdrew Cash | C80: OUT | D80: 1064 | E80: Cash | F80: Owner Drawings | H80: N/A | K80: Samer Ayoub (CEO) | L80: Owner | N80: 0 | O80: =IF(OR(D80="", N80=""), "", ROUND(D80 * N80 / 100, 2)) -> 0 | P80: =IF(D80="", "", D80 + O80) -> 1064 | Q80: Paid | R80: Owner Personal Use
A81: 45994 | B81: cold dowan+Baity | C81: OUT | D81: 100 | E81: Cash | F81: Material Purchase | H81: Material/Tools | K81: Shaaban+Baity | L81: Supplier | N81: 15 | O81: =IF(OR(D81="", N81=""), "", ROUND(D81 * N81 / 100, 2)) -> 15 | P81: =IF(D81="", "", D81 + O81) -> 115 | Q81: Paid | R81: Company General Expense
A82: 45994 | B82: Bearing+other | C82: OUT | D82: 145 | E82: Cash | F82: Material Purchase | H82: Material/Tools | K82: TBD | L82: Supplier | N82: 0 | O82: =IF(OR(D82="", N82=""), "", ROUND(D82 * N82 / 100, 2)) -> 0 | P82: =IF(D82="", "", D82 + O82) -> 145 | Q82: Paid | R82: Company General Expense
A83: 45995 | B83: Hotel+Dabbab bill | C83: OUT | D83: 810 | E83: Cash | F83: Transport Expense | H83: Food for Team | K83: Naeem+Tahir | L83: Supplier | N83: 0 | O83: =IF(OR(D83="", N83=""), "", ROUND(D83 * N83 / 100, 2)) -> 0 | P83: =IF(D83="", "", D83 + O83) -> 810 | Q83: Paid | R83: Company General Expense
A84: 45995 | B84: bowwor paid to younus | C84: OUT | D84: 212 | E84: Cash | F84: Settlement | H84: N/A | K84: Younus | L84: Supplier | N84: 0 | O84: =IF(OR(D84="", N84=""), "", ROUND(D84 * N84 / 100, 2)) -> 0 | P84: =IF(D84="", "", D84 + O84) -> 212 | Q84: Paid | R84: Company General Expense
A85: 45995 | B85: Workshop Electricity bill paid | C85: OUT | D85: 500 | E85: Cash | F85: Electricity Expense | H85: Other | K85: Tariq Yamni workshop | L85: Supplier | N85: 0 | O85: =IF(OR(D85="", N85=""), "", ROUND(D85 * N85 / 100, 2)) -> 0 | P85: =IF(D85="", "", D85 + O85) -> 500 | Q85: Paid | R85: Company General Expense
A86: 45995 | B86: Material Purchase for epoxy work in jazzan | C86: OUT | D86: 491 | E86: Cash | F86: Material Purchase | G86: Epoxy Paint Project Jazzan | H86: Material/Tools | K86: TBD | L86: Supplier | N86: 15 | O86: =IF(OR(D86="", N86=""), "", ROUND(D86 * N86 / 100, 2)) -> 73.65 | P86: =IF(D86="", "", D86 + O86) -> 564.65 | Q86: Paid | R86: Project Expense
A87: 45995 | B87: Payment Transfer | C87: OUT | D87: 850 | E87: Cash | F87: Material Purchase | H87: Material/Tools | K87: Saeed/Milling | L87: Supplier | N87: 0 | O87: =IF(OR(D87="", N87=""), "", ROUND(D87 * N87 / 100, 2)) -> 0 | P87: =IF(D87="", "", D87 + O87) -> 850 | Q87: Paid | R87: Company General Expense
A88: 45995 | B88: Payment receive | C88: IN | D88: 1700 | E88: Cash | F88: Project Income | G88: Fabrication of Rollers | H88: N/A | K88: Fosam Company Limited | L88: Client | N88: 15 | O88: =IF(OR(D88="", N88=""), "", ROUND(D88 * N88 / 100, 2)) -> 255 | P88: =IF(D88="", "", D88 + O88) -> 1955 | Q88: Paid | R88: 100% Payment Received
A89: 45995 | B89: Material Purchase for rollers | C89: OUT | D89: 380 | E89: Cash | F89: Material Purchase | G89: Fabrication of Rollers | H89: Material/Tools | K89: TBD | L89: Supplier | N89: 15 | O89: =IF(OR(D89="", N89=""), "", ROUND(D89 * N89 / 100, 2)) -> 57 | P89: =IF(D89="", "", D89 + O89) -> 437 | Q89: Paid | R89: Project Expense
A90: 45995 | B90: Material Purchase for Maintenance of Track Adjuster Cylinder Reviva | C90: OUT | D90: 1000 | E90: Cash | F90: Repair & Maintenance Expense | G90: Maintenance of Track Adjuster Cylinder | H90: Material/Tools | K90: Arif bangali | L90: Supplier | N90: 0 | O90: =IF(OR(D90="", N90=""), "", ROUND(D90 * N90 / 100, 2)) -> 0 | P90: =IF(D90="", "", D90 + O90) -> 1000 | Q90: Paid | R90: Project Expense
A91: 45997 | B91: Epoxy project Material Purchasing | C91: OUT | D91: 500 | E91: Cash | F91: Material Purchase | G91: Epoxy Paint Project Jazzan | H91: Material/Tools | K91: TBD | L91: Supplier | N91: 0 | O91: =IF(OR(D91="", N91=""), "", ROUND(D91 * N91 / 100, 2)) -> 0 | P91: =IF(D91="", "", D91 + O91) -> 500 | Q91: Paid | R91: Project Expense
A92: 45997 | B92: Epoxy project Material Purchasing | C92: OUT | D92: 74 | E92: Cash | F92: Material Purchase | G92: Epoxy Paint Project Jazzan | H92: Material/Tools | K92: TBD | L92: Supplier | N92: 15 | O92: =IF(OR(D92="", N92=""), "", ROUND(D92 * N92 / 100, 2)) -> 11.1 | P92: =IF(D92="", "", D92 + O92) -> 85.1 | Q92: Paid | R92: Project Expense
A93: 45998 | B93: Transport provide from jazzan to jeddah Labour | C93: OUT | D93: 300 | E93: Cash | F93: Transport Expense | G93: Epoxy Paint Project Jazzan | H93: Transport Expense | K93: TBD | L93: Supplier | N93: 0 | O93: =IF(OR(D93="", N93=""), "", ROUND(D93 * N93 / 100, 2)) -> 0 | P93: =IF(D93="", "", D93 + O93) -> 300 | Q93: Paid | R93: Project Expense
A94: 45999 | B94: Fuel for owner Car | C94: OUT | D94: 43.49 | E94: Cash | F94: Fuel Expense | H94: Fuel Expense | K94: TBD | L94: Supplier | N94: 15 | O94: =IF(OR(D94="", N94=""), "", ROUND(D94 * N94 / 100, 2)) -> 6.52 | P94: =IF(D94="", "", D94 + O94) -> 50.01 | Q94: Paid | R94: Company General Expense
A95: 45999 | B95: Fuel for Nissan | C95: OUT | D95: 149.2 | E95: Cash | F95: Fuel Expense | H95: Fuel Expense | K95: TBD | L95: Supplier | N95: 15 | O95: =IF(OR(D95="", N95=""), "", ROUND(D95 * N95 / 100, 2)) -> 22.38 | P95: =IF(D95="", "", D95 + O95) -> 171.58 | Q95: Paid | R95: Company General Expense
A96: 45999 | B96: Mobile Package for Shoaib | C96: OUT | D96: 100 | E96: Cash | F96: Mobile Package Expense | H96: Mobile Package Expense | K96: Shoaib Umar | L96: Employee | N96: 15 | O96: =IF(OR(D96="", N96=""), "", ROUND(D96 * N96 / 100, 2)) -> 15 | P96: =IF(D96="", "", D96 + O96) -> 115 | Q96: Paid | R96: Company General Expense
A97: 45999 | B97: Bank Charges Detacted from compnay account | C97: OUT | D97: 115 | E97: Cash | F97: Bank Charges | H97: Bank Charges | K97: SNB | L97: Supplier | N97: 0 | O97: =IF(OR(D97="", N97=""), "", ROUND(D97 * N97 / 100, 2)) -> 0 | P97: =IF(D97="", "", D97 + O97) -> 115 | Q97: Paid | R97: Company General Expense
A98: 45999 | B98: Owner Withdrew Cash | C98: OUT | D98: 1330 | E98: Cash | F98: Owner Drawings | H98: N/A | K98: Samer Ayoub (CEO) | L98: Owner | N98: 0 | O98: =IF(OR(D98="", N98=""), "", ROUND(D98 * N98 / 100, 2)) -> 0 | P98: =IF(D98="", "", D98 + O98) -> 1330 | Q98: Paid | R98: Owner Personal Use
A99: 45999 | B99: company commission | C99: OUT | D99: 230 | E99: Cash | F99: Company Office Expense | H99: N/A | K99: TBD | L99: Supplier | N99: 0 | O99: =IF(OR(D99="", N99=""), "", ROUND(D99 * N99 / 100, 2)) -> 0 | P99: =IF(D99="", "", D99 + O99) -> 230 | Q99: Paid | R99: Company General Expense
A100: 46000 | B100: Payment Received of Roller Project | C100: IN | D100: 14925 | E100: Cash | F100: Project Income | G100: Fabrication of New Roller/8mm | H100: N/A | K100: Prainsa Concrete Company | L100: Client | M100: INV/2025/00028 | N100: 15 | O100: =IF(OR(D100="", N100=""), "", ROUND(D100 * N100 / 100, 2)) -> 2238.75 | P100: =IF(D100="", "", D100 + O100) -> 17163.75 | Q100: Paid | R100: 100% Paymnet Received
A101: 46000 | B101: Fabrication of Rollers | C101: OUT | D101: 5000 | E101: Cash | F101: Repair & Maintenance Expense | G101: Fabrication of New Roller/8mm | H101: Material/Tools | K101: Arif bangali | L101: Supplier | N101: 0 | O101: =IF(OR(D101="", N101=""), "", ROUND(D101 * N101 / 100, 2)) -> 0 | P101: =IF(D101="", "", D101 + O101) -> 5000 | Q101: Paid | R101: Project Expense
A102: 46000 | B102: Project expense of Roller | C102: OUT | D102: 4850 | E102: Cash | F102: Material Purchase | G102: Fabrication of New Roller/8mm | H102: Material/Tools | K102: TBD | L102: Supplier | N102: 15 | O102: =IF(OR(D102="", N102=""), "", ROUND(D102 * N102 / 100, 2)) -> 727.5 | P102: =IF(D102="", "", D102 + O102) -> 5577.5 | Q102: Paid | R102: Project Expense
...

Sheet Projects
A1: Project Name | B1: Client Name | C1: Contract Value (Excl. VAT) | D1: VAT 15% | E1: Contract Incl. VAT | F1: Required 50% Advance (Incl. VAT) | G1: Total Income | H1: Total Expense | I1: Net Profit / Loss | J1: Remaining Amount
A2: SS316 Pipeline Work | B2: Oud Lover Factory | C2: 4000 | D2: =IF(C2="","",ROUND(C2*0.15,2)) -> 600 | E2: =IF(C2="","",C2+D2) -> 4600 | F2: =IF(E2="","",E2*0.5) -> 2300 | G2: =IF($A2="","", SUMIFS(Transactions!$P:$P, Transactions!$G:$G,$A2, Transactions!$C:$C,"IN", Transactions!$Q:$Q,"*Paid*")) -> 4600 | H2: =IF($A2="","", SUMIFS(Transactions!$P:$P, Transactions!$G:$G,$A2, Transactions!$C:$C,"OUT")) -> 5499.95 | I2: =IF(C2="","",C2-H2) -> -1499.95 | J2: =IF(E2="","",E2-G2) -> 0
A3: Instalation of Sign Board | B3: Feedco Investment Company | C3: 2000 | D3: =IF(C3="","",ROUND(C3*0.15,2)) -> 300 | E3: =IF(C3="","",C3+D3) -> 2300 | F3: =IF(E3="","",E3*0.5) -> 1150 | G3: =IF($A3="","", SUMIFS(Transactions!$P:$P, Transactions!$G:$G,$A3, Transactions!$C:$C,"IN", Transactions!$Q:$Q,"*Paid*")) -> 2300 | H3: =IF($A3="","", SUMIFS(Transactions!$P:$P, Transactions!$G:$G,$A3, Transactions!$C:$C,"OUT")) -> 890 | I3: =IF(C3="","",C3-H3) -> 1110 | J3: =IF(E3="","",E3-G3) -> 0
A4: Fabrication of Steel Ramp | B4: Bahri Logistics | C4: 14850 | D4: =IF(C4="","",ROUND(C4*0.15,2)) -> 2227.5 | E4: =IF(C4="","",C4+D4) -> 17077.5 | F4: =IF(E4="","",E4*0.5) -> 8538.75 | G4: =IF($A4="","", SUMIFS(Transactions!$P:$P, Transactions!$G:$G,$A4, Transactions!$C:$C,"IN", Transactions!$Q:$Q,"*Paid*")) -> 17077.5 | H4: =IF($A4="","", SUMIFS(Transactions!$P:$P, Transactions!$G:$G,$A4, Transactions!$C:$C,"OUT")) -> 7161.97 | I4: =IF(C4="","",C4-H4) -> 7688.03 | J4: =IF(E4="","",E4-G4) -> 0
A5: Fabrication of SS+Steel Pillows | B5: Fosam Company Limited | C5: 27000 | D5: =IF(C5="","",ROUND(C5*0.15,2)) -> 4050 | E5: =IF(C5="","",C5+D5) -> 31050 | F5: =IF(E5="","",E5*0.5) -> 15525 | G5: =IF($A5="","", SUMIFS(Transactions!$P:$P, Transactions!$G:$G,$A5, Transactions!$C:$C,"IN", Transactions!$Q:$Q,"Paid")) -> 31050 | H5: =IF($A5="","", SUMIFS(Transactions!$P:$P, Transactions!$G:$G,$A5, Transactions!$C:$C,"OUT")) -> 12395 | I5: =IF(C5="","",C5-H5) -> 14605 | J5: =IF(E5="","",E5-G5) -> 0
A6: Fabrication of Steel Shose for Forklift | B6: Bahri Logistics | C6: 4300 | D6: =IF(C6="","",ROUND(C6*0.15,2)) -> 645 | E6: =IF(C6="","",C6+D6) -> 4945 | F6: =IF(E6="","",E6*0.5) -> 2472.5 | G6: =IF($A6="","", SUMIFS(Transactions!$P:$P, Transactions!$G:$G,$A6, Transactions!$C:$C,"IN", Transactions!$Q:$Q,"Paid")) -> 4945 | H6: =IF($A6="","", SUMIFS(Transactions!$P:$P, Transactions!$G:$G,$A6, Transactions!$C:$C,"OUT")) -> 1511.39 | I6: =IF(C6="","",C6-H6) -> 2788.61 | J6: =IF(E6="","",E6-G6) -> 0
A7: Fitting of Press Roller | B7: Feedco Investment Company | C7: 8800 | D7: =IF(C7="","",ROUND(C7*0.15,2)) -> 1320 | E7: =IF(C7="","",C7+D7) -> 10120 | F7: =IF(E7="","",E7*0.5) -> 5060 | G7: =IF($A7="","", SUMIFS(Transactions!$P:$P, Transactions!$G:$G,$A7, Transactions!$C:$C,"IN", Transactions!$Q:$Q,"Paid")) -> 10120 | H7: =IF($A7="","", SUMIFS(Transactions!$P:$P, Transactions!$G:$G,$A7, Transactions!$C:$C,"OUT")) -> 4450 | I7: =IF(C7="","",C7-H7) -> 4350 | J7: =IF(E7="","",E7-G7) -> 0
A8: Epoxy Paint Project Jazzan | B8: Company Rosomat/Wasim | C8: 29900 | D8: =IF(C8="","",ROUND(C8*0.15,2)) -> 4485 | E8: =IF(C8="","",C8+D8) -> 34385 | F8: =IF(E8="","",E8*0.5) -> 17192.5 | G8: =IF($A8="","", SUMIFS(Transactions!$P:$P, Transactions!$G:$G,$A8, Transactions!$C:$C,"IN", Transactions!$Q:$Q,"Paid")) -> 29905 | H8: =IF($A8="","", SUMIFS(Transactions!$P:$P, Transactions!$G:$G,$A8, Transactions!$C:$C,"OUT")) -> 21164.75 | I8: =IF(C8="","",C8-H8) -> 8735.25 | J8: =IF(E8="","",E8-G8) -> 4480
A9: Maintenance of Loader | B9: Sapac Company | C9: 5000 | D9: =IF(C9="","",ROUND(C9*0.15,2)) -> 750 | E9: =IF(C9="","",C9+D9) -> 5750 | F9: =IF(E9="","",E9*0.5) -> 2875 | G9: =IF($A9="","", SUMIFS(Transactions!$P:$P, Transactions!$G:$G,$A9, Transactions!$C:$C,"IN", Transactions!$Q:$Q,"Paid")) -> 5750 | H9: =IF($A9="","", SUMIFS(Transactions!$P:$P, Transactions!$G:$G,$A9, Transactions!$C:$C,"OUT")) -> 2550 | I9: =IF(C9="","",C9-H9) -> 2450 | J9: =IF(E9="","",E9-G9) -> 0
A10: Fabrication of Rollers | B10: Fosam Company Limited | C10: 1700 | D10: =IF(C10="","",ROUND(C10*0.15,2)) -> 255 | E10: =IF(C10="","",C10+D10) -> 1955 | F10: =IF(E10="","",E10*0.5) -> 977.5 | G10: =IF($A10="","", SUMIFS(Transactions!$P:$P, Transactions!$G:$G,$A10, Transactions!$C:$C,"IN", Transactions!$Q:$Q,"Paid")) -> 1955 | H10: =IF($A10="","", SUMIFS(Transactions!$P:$P, Transactions!$G:$G,$A10, Transactions!$C:$C,"OUT")) -> 437 | I10: =IF(C10="","",C10-H10) -> 1263 | J10: =IF(E10="","",E10-G10) -> 0
A11: Fabrication of New Roller/8mm | B11: Prainsa Concrete Company | C11: 14925 | D11: =IF(C11="","",ROUND(C11*0.15,2)) -> 2238.75 | E11: =IF(C11="","",C11+D11) -> 17163.75 | F11: =IF(E11="","",E11*0.5) -> 8581.875 | G11: =IF($A11="","", SUMIFS(Transactions!$P:$P, Transactions!$G:$G,$A11, Transactions!$C:$C,"IN", Transactions!$Q:$Q,"Paid")) -> 17163.75 | H11: =IF($A11="","", SUMIFS(Transactions!$P:$P, Transactions!$G:$G,$A11, Transactions!$C:$C,"OUT")) -> 10577.5 | I11: =IF(C11="","",C11-H11) -> 4347.5 | J11: =IF(E11="","",E11-G11) -> 0
A12: Fabrication stainless steel 304 screw | B12: Feedco Investment Company | C12: 4000 | D12: =IF(C12="","",ROUND(C12*0.15,2)) -> 600 | E12: =IF(C12="","",C12+D12) -> 4600 | F12: =IF(E12="","",E12*0.5) -> 2300 | G12: =IF($A12="","", SUMIFS(Transactions!$P:$P, Transactions!$G:$G,$A12, Transactions!$C:$C,"IN", Transactions!$Q:$Q,"Paid")) -> 4600 | H12: =IF($A12="","", SUMIFS(Transactions!$P:$P, Transactions!$G:$G,$A12, Transactions!$C:$C,"OUT")) -> 2563.49 | I12: =IF(C12="","",C12-H12) -> 1436.51 | J12: =IF(E12="","",E12-G12) -> 0
A13: Modification of aluminum cover | B13: Fosam Company Limited | C13: 750 | D13: =IF(C13="","",ROUND(C13*0.15,2)) -> 112.5 | E13: =IF(C13="","",C13+D13) -> 862.5 | F13: =IF(E13="","",E13*0.5) -> 431.25 | G13: =IF($A13="","", SUMIFS(Transactions!$P:$P, Transactions!$G:$G,$A13, Transactions!$C:$C,"IN", Transactions!$Q:$Q,"Paid")) -> 862.5 | H13: =IF($A13="","", SUMIFS(Transactions!$P:$P, Transactions!$G:$G,$A13, Transactions!$C:$C,"OUT")) -> 345 | I13: =IF(C13="","",C13-H13) -> 405 | J13: =IF(E13="","",E13-G13) -> 0
A14: Maintenance of Track Adjuster Cylinder | B14: Gems Reviva Company | C14: 3600 | D14: =IF(C14="","",ROUND(C14*0.15,2)) -> 540 | E14: =IF(C14="","",C14+D14) -> 4140 | F14: =IF(E14="","",E14*0.5) -> 2070 | G14: =IF($A14="","", SUMIFS(Transactions!$P:$P, Transactions!$G:$G,$A14, Transactions!$C:$C,"IN", Transactions!$Q:$Q,"Paid")) -> 0 | H14: =IF($A14="","", SUMIFS(Transactions!$P:$P, Transactions!$G:$G,$A14, Transactions!$C:$C,"OUT")) -> 1178.7 | I14: =IF(C14="","",C14-H14) -> 2421.3 | J14: =IF(E14="","",E14-G14) -> 4140
A15: Maintenance of Rotary Lobe Blower | B15: Gems Reviva Company | C15: 8500 | D15: =IF(C15="","",ROUND(C15*0.15,2)) -> 1275 | E15: =IF(C15="","",C15+D15) -> 9775 | F15: =IF(E15="","",E15*0.5) -> 4887.5 | G15: =IF($A15="","", SUMIFS(Transactions!$P:$P, Transactions!$G:$G,$A15, Transactions!$C:$C,"IN", Transactions!$Q:$Q,"Paid")) -> 0 | H15: =IF($A15="","", SUMIFS(Transactions!$P:$P, Transactions!$G:$G,$A15, Transactions!$C:$C,"OUT")) -> 4846.45 | I15: =IF(C15="","",C15-H15) -> 3653.55 | J15: =IF(E15="","",E15-G15) -> 9775
A16: Supply of Water Sensor | B16: Modern Building Leaders | C16: 5000 | D16: =IF(C16="","",ROUND(C16*0.15,2)) -> 750 | E16: =IF(C16="","",C16+D16) -> 5750 | F16: =IF(E16="","",E16*0.5) -> 2875 | G16: =IF($A16="","", SUMIFS(Transactions!$P:$P, Transactions!$G:$G,$A16, Transactions!$C:$C,"IN", Transactions!$Q:$Q,"Paid")) -> 5750 | H16: =IF($A16="","", SUMIFS(Transactions!$P:$P, Transactions!$G:$G,$A16, Transactions!$C:$C,"OUT")) -> 0 | I16: =IF(C16="","",C16-H16) -> 5000 | J16: =IF(E16="","",E16-G16) -> 0
... A29: Fabrication of Doors/15mm 2pc | B29: Feedco Investment Company | C29: 13540 | D29: =IF(C29="","",ROUND(C29*0.15,2)) -> 2031 | E29: =IF(C29="","",C29+D29) -> 15571 | F29: =IF(E29="","",E29*0.5) -> 7785.5 | G29: =IF($A29="","", SUMIFS(Transactions!$P:$P, Transactions!$G:$G,$A29, Transactions!$C:$C,"IN", Transactions!$Q:$Q,"Paid")) -> 15569.85 | H29: =IF($A29="","", SUMIFS(Transactions!$P:$P, Transactions!$G:$G,$A29, Transactions!$C:$C,"OUT")) -> 7122.87 | I29: =IF(C29="","",C29-H29) -> 6417.13 | J29: =IF(E29="","",E29-G29) -> 1.15
A30: PO-0155+PO-0156 (ClipBoard+wood Aternator) | B30: Al-Markaz company | C30: 23080 | D30: =IF(C30="","",ROUND(C30*0.15,2)) -> 3462 | E30: =IF(C30="","",C30+D30) -> 26542 | F30: =IF(E30="","",E30*0.5) -> 13271 | G30: =IF($A30="","", SUMIFS(Transactions!$P:$P, Transactions!$G:$G,$A30, Transactions!$C:$C,"IN", Transactions!$Q:$Q,"Paid")) -> 35769.6 | H30: =IF($A30="","", SUMIFS(Transactions!$P:$P, Transactions!$G:$G,$A30, Transactions!$C:$C,"OUT")) -> 27300.75 | I30: =IF(C30="","",C30-H30) -> -4220.75 | J30: =IF(E30="","",E30-G30) -> -9227.6 | K30: Amount of Two invoices
A31: Maintenance of Bole Drum | B31: Emar Ayan Industrial Factory | C31: 8800 | D31: =IF(C31="","",ROUND(C31*0.15,2)) -> 1320 | E31: =IF(C31="","",C31+D31) -> 10120 | F31: =IF(E31="","",E31*0.5) -> 5060 | G31: =IF($A31="","", SUMIFS(Transactions!$P:$P, Transactions!$G:$G,$A31, Transactions!$C:$C,"IN", Transactions!$Q:$Q,"Paid")) -> 5060 | H31: =IF($A31="","", SUMIFS(Transactions!$P:$P, Transactions!$G:$G,$A31, Transactions!$C:$C,"OUT")) -> 350 | I31: =IF(C31="","",C31-H31) -> 8450 | J31: =IF(E31="","",E31-G31) -> 5060
D32: =IF(C32="","",ROUND(C32*0.15,2)) | E32: =IF(C32="","",C32+D32) | F32: =IF(E32="","",E32*0.5) | G32: =IF($A32="","", SUMIFS(Transactions!$P:$P, Transactions!$G:$G,$A32, Transactions!$C:$C,"IN", Transactions!$Q:$Q,"Paid")) | H32: =IF($A32="","", SUMIFS(Transactions!$P:$P, Transactions!$G:$G,$A32, Transactions!$C:$C,"OUT")) | I32: =IF(C32="","",C32-H32) | J32: =IF(E32="","",E32-G32)
D33: =IF(C33="","",ROUND(C33*0.15,2)) | E33: =IF(C33="","",C33+D33) | F33: =IF(E33="","",E33*0.5) | G33: =IF($A33="","", SUMIFS(Transactions!$P:$P, Transactions!$G:$G,$A33, Transactions!$C:$C,"IN", Transactions!$Q:$Q,"Paid")) | H33: =IF($A33="","", SUMIFS(Transactions!$P:$P, Transactions!$G:$G,$A33, Transactions!$C:$C,"OUT")) | I33: =IF(C33="","",C33-H33) | J33: =IF(E33="","",E33-G33)
D34: =IF(C34="","",ROUND(C34*0.15,2)) | E34: =IF(C34="","",C34+D34) | F34: =IF(E34="","",E34*0.5) | G34: =IF($A34="","", SUMIFS(Transactions!$P:$P, Transactions!$G:$G,$A34, Transactions!$C:$C,"IN", Transactions!$Q:$Q,"Paid")) | H34: =IF($A34="","", SUMIFS(Transactions!$P:$P, Transactions!$G:$G,$A34, Transactions!$C:$C,"OUT")) | I34: =IF(C34="","",C34-H34) | J34: =IF(E34="","",E34-G34)
D35: =IF(C35="","",ROUND(C35*0.15,2)) | E35: =IF(C35="","",C35+D35) | F35: =IF(E35="","",E35*0.5) | G35: =IF($A35="","", SUMIFS(Transactions!$P:$P, Transactions!$G:$G,$A35, Transactions!$C:$C,"IN", Transactions!$Q:$Q,"Paid")) | H35: =IF($A35="","", SUMIFS(Transactions!$P:$P, Transactions!$G:$G,$A35, Transactions!$C:$C,"OUT")) | I35: =IF(C35="","",C35-H35) | J35: =IF(E35="","",E35-G35)
D36: =IF(C36="","",ROUND(C36*0.15,2)) | E36: =IF(C36="","",C36+D36) | F36: =IF(E36="","",E36*0.5) | G36: =IF($A36="","", SUMIFS(Transactions!$P:$P, Transactions!$G:$G,$A36, Transactions!$C:$C,"IN", Transactions!$Q:$Q,"Paid")) | H36: =IF($A36="","", SUMIFS(Transactions!$P:$P, Transactions!$G:$G,$A36, Transactions!$C:$C,"OUT")) | I36: =IF(C36="","",C36-H36) | J36: =IF(E36="","",E36-G36)
D37: =IF(C37="","",ROUND(C37*0.15,2)) | E37: =IF(C37="","",C37+D37) | F37: =IF(E37="","",E37*0.5) | G37: =IF($A37="","", SUMIFS(Transactions!$P:$P, Transactions!$G:$G,$A37, Transactions!$C:$C,"IN", Transactions!$Q:$Q,"Paid")) | H37: =IF($A37="","", SUMIFS(Transactions!$P:$P, Transactions!$G:$G,$A37, Transactions!$C:$C,"OUT")) | I37: =IF(C37="","",C37-H37) | J37: =IF(E37="","",E37-G37)
D38: =IF(C38="","",ROUND(C38*0.15,2)) | E38: =IF(C38="","",C38+D38) | F38: =IF(E38="","",E38*0.5) | G38: =IF($A38="","", SUMIFS(Transactions!$P:$P, Transactions!$G:$G,$A38, Transactions!$C:$C,"IN", Transactions!$Q:$Q,"Paid")) | H38: =IF($A38="","", SUMIFS(Transactions!$P:$P, Transactions!$G:$G,$A38, Transactions!$C:$C,"OUT")) | I38: =IF(C38="","",C38-H38) | J38: =IF(E38="","",E38-G38)
D39: =IF(C39="","",ROUND(C39*0.15,2)) | E39: =IF(C39="","",C39+D39) | F39: =IF(E39="","",E39*0.5) | G39: =IF($A39="","", SUMIFS(Transactions!$P:$P, Transactions!$G:$G,$A39, Transactions!$C:$C,"IN", Transactions!$Q:$Q,"Paid")) | H39: =IF($A39="","", SUMIFS(Transactions!$P:$P, Transactions!$G:$G,$A39, Transactions!$C:$C,"OUT")) | I39: =IF(C39="","",C39-H39) | J39: =IF(E39="","",E39-G39)
D40: =IF(C40="","",ROUND(C40*0.15,2)) | E40: =IF(C40="","",C40+D40) | F40: =IF(E40="","",E40*0.5) | G40: =IF($A40="","", SUMIFS(Transactions!$P:$P, Transactions!$G:$G,$A40, Transactions!$C:$C,"IN", Transactions!$Q:$Q,"Paid")) | H40: =IF($A40="","", SUMIFS(Transactions!$P:$P, Transactions!$G:$G,$A40, Transactions!$C:$C,"OUT")) | I40: =IF(C40="","",C40-H40) | J40: =IF(E40="","",E40-G40)
D41: =IF(C41="","",ROUND(C41*0.15,2)) | E41: =IF(C41="","",C41+D41) | F41: =IF(E41="","",E41*0.5) | G41: =IF($A41="","", SUMIFS(Transactions!$P:$P, Transactions!$G:$G,$A41, Transactions!$C:$C,"IN", Transactions!$Q:$Q,"Paid")) | H41: =IF($A41="","", SUMIFS(Transactions!$P:$P, Transactions!$G:$G,$A41, Transactions!$C:$C,"OUT")) | I41: =IF(C41="","",C41-H41) | J41: =IF(E41="","",E41-G41)
D42: =IF(C42="","",ROUND(C42*0.15,2)) | E42: =IF(C42="","",C42+D42) | F42: =IF(E42="","",E42*0.5) | G42: =IF($A42="","", SUMIFS(Transactions!$P:$P, Transactions!$G:$G,$A42, Transactions!$C:$C,"IN", Transactions!$Q:$Q,"Paid")) | H42: =IF($A42="","", SUMIFS(Transactions!$P:$P, Transactions!$G:$G,$A42, Transactions!$C:$C,"OUT")) | I42: =IF(C42="","",C42-H42) | J42: =IF(E42="","",E42-G42)
D43: =IF(C43="","",ROUND(C43*0.15,2)) | E43: =IF(C43="","",C43+D43) | F43: =IF(E43="","",E43*0.5) | G43: =IF($A43="","", SUMIFS(Transactions!$P:$P, Transactions!$G:$G,$A43, Transactions!$C:$C,"IN", Transactions!$Q:$Q,"Paid")) | H43: =IF($A43="","", SUMIFS(Transactions!$P:$P, Transactions!$G:$G,$A43, Transactions!$C:$C,"OUT")) | I43: =IF(C43="","",C43-H43) | J43: =IF(E43="","",E43-G43)
... D2000: =IF(C2000="","",ROUND(C2000*0.15,2)) | E2000: =IF(C2000="","",C2000+D2000) | F2000: =IF(E2000="","",E2000*0.5) | G2000: =IF($A2000="","", SUMIFS(Transactions!$P:$P, Transactions!$G:$G,$A2000, Transactions!$C:$C,"IN", Transactions!$Q:$Q,"Paid")) | H2000: =IF($A2000="","", SUMIFS(Transactions!$P:$P, Transactions!$G:$G,$A2000, Transactions!$C:$C,"OUT")) | I2000: =IF(C2000="","",C2000-H2000) | J2000: =IF(E2000="","",E2000-G2000)

Sheet Accounts_Summary
A1: Account Name | B1: Total IN | C1: Total OUT | D1: Balance
A2: Cash | B2: =SUMIFS(Transactions!$P:$P,Transactions!$C:$C,"IN",Transactions!$E:$E,$A2) -> 418456.21 | C2: =SUMIFS(Transactions!$P:$P,Transactions!$C:$C,"OUT",Transactions!$E:$E,$A2) -> 434675.71 | D2: =B2-C2 -> -16219.5 | E2: With VAT
A3: Bank | B3: =SUMIFS(Transactions!$P:$P,Transactions!$C:$C,"IN",Transactions!$E:$E,$A3) -> 0 | C3: =SUMIFS(Transactions!$P:$P,Transactions!$C:$C,"OUT",Transactions!$E:$E,$A3) -> 0 | D3: =B3-C3 -> 0 | E3: With VAT
A4: Owner Contribution | B4: =SUMIFS(Transactions!$P:$P,Transactions!$C:$C,"IN",Transactions!$E:$E,$A4) -> 0 | C4: =SUMIFS(Transactions!$P:$P,Transactions!$C:$C,"OUT",Transactions!$E:$E,$A4) -> 0 | D4: =B4-C4 -> 0 | E4: Without VAT Amount
A5: Owner Drawings | B5: =SUMIFS(Transactions!$D:$D, Transactions!$F:$F, "Owner Drawings", Transactions!$C:$C, "IN") -> 0 | C5: =SUMIFS(Transactions!$D:$D, Transactions!$F:$F, "Owner Drawings", Transactions!$C:$C, "OUT") -> 35145 | D5: =B5 - C5 -> -35145 | E5: Without VAT Amount
A6: Accounts Receivable | B6: =SUMIFS(Transactions!$D:$D, Transactions!$E:$E, "Accounts Receivable", Transactions!$C:$C, "IN") -> 30052.5 | C6: =SUMIFS(Transactions!$D:$D, Transactions!$E:$E, "Accounts Receivable", Transactions!$C:$C, "OUT") -> 17952.5 | D6: =B6 - C6 -> 12100 | E6: Without VAT Amount
A7: Accounts Payable | B7: =SUMIFS(Transactions!$D:$D, Transactions!$E:$E, "Accounts Payable", Transactions!$C:$C, "IN") -> 3134.79 | C7: =SUMIFS(Transactions!$D:$D, Transactions!$E:$E, "Accounts Payable", Transactions!$C:$C, "OUT") -> 8734.79 | D7: =B7-C7 -> -5600 | E7: Without VAT Amount
A8: Employee Payable | B8: =SUMIFS(Transactions!$D:$D, Transactions!$E:$E, "Employee Payable", Transactions!$C:$C, "IN") -> 0 | C8: =SUMIFS(Transactions!$D:$D, Transactions!$E:$E, "Employee Payable", Transactions!$C:$C, "OUT") -> 0 | D8: =B8 - C8 -> 0 | E8: Without VAT Amount
A9: Employee Advance | B9: =SUMIFS(Transactions!$D:$D, Transactions!$E:$E, "Employee Advance", Transactions!$C:$C, "IN") -> 0 | C9: =SUMIFS(Transactions!$D:$D, Transactions!$E:$E, "Employee Advance", Transactions!$C:$C, "OUT") -> 17486 | D9: =B9-C9 -> -17486 | E9: Without VAT Amount

Sheet Tax Report
A1: Month | B1: Year | C1: Total Sales (Excl. VAT) | D1: Output VAT 15% | E1: Total Purchases (Excl. VAT) | F1: Input VAT 15% | G1: Net VAT Payable
A2: 11 | B2: 2025 | C2: =IF(OR($A2="",$B2=""),"", SUMIFS(Transactions!$D:$D, Transactions!$C:$C,"IN", Transactions!$L:$L,"Client", Transactions!$Q:$Q,"*Paid*", Transactions!$A:$A,">="&DATE($B2,$A2,1), Transactions!$A:$A,"<"&EDATE(DATE($B2,$A2,1),1) ) ) -> 40425 | D2: =IF(OR($A2="",$B2=""),"", SUMIFS(Transactions!$O:$O, Transactions!$C:$C,"IN", Transactions!$L:$L,"Client", Transactions!$Q:$Q,"*Paid*", Transactions!$A:$A,">="&DATE($B2,$A2,1), Transactions!$A:$A,"<"&EDATE(DATE($B2,$A2,1),1) ) ) -> 4950 | E2: =SUMIFS( Transactions!$D:$D, Transactions!$C:$C,"OUT", Transactions!$E:$E,"Cash", Transactions!$A:$A,">=" & DATE($B2,$A2,1), Transactions!$A:$A,"<" & DATE($B2,$A2+1,1) ) -> 30410.05 | F2: =SUMIFS( Transactions!$O:$O, Transactions!$C:$C,"OUT", Transactions!$E:$E,"Cash", Transactions!$A:$A,">=" & DATE($B2,$A2,1), Transactions!$A:$A,"<" & DATE($B2,$A2+1,1) ) -> 2824.11 | G2: =IF(OR(D2="",F2=""),"",D2-F2) -> 2125.89
A3: 12 | B3: 2025 | C3: =IF(OR($A3="",$B3=""),"", SUMIFS(Transactions!$D:$D, Transactions!$C:$C,"IN", Transactions!$L:$L,"Client", Transactions!$Q:$Q,"*Paid*", Transactions!$A:$A,">="&DATE($B3,$A3,1), Transactions!$A:$A,"<"&EDATE(DATE($B3,$A3,1),1) ) ) -> 67827.5 | D3: =IF(OR($A3="",$B3=""),"", SUMIFS(Transactions!$O:$O, Transactions!$C:$C,"IN", Transactions!$L:$L,"Client", Transactions!$Q:$Q,"*Paid*", Transactions!$A:$A,">="&DATE($B3,$A3,1), Transactions!$A:$A,"<"&EDATE(DATE($B3,$A3,1),1) ) ) -> 6476.25 | E3: =SUMIFS( Transactions!$D:$D, Transactions!$C:$C,"OUT", Transactions!$E:$E,"Cash", Transactions!$A:$A,">=" & DATE($B3,$A3,1), Transactions!$A:$A,"<" & DATE($B3,$A3+1,1) ) -> 76881.28 | F3: =SUMIFS( Transactions!$O:$O, Transactions!$C:$C,"OUT", Transactions!$E:$E,"Cash", Transactions!$A:$A,">=" & DATE($B3,$A3,1), Transactions!$A:$A,"<" & DATE($B3,$A3+1,1) ) -> 3566.25 | G3: =IF(OR(D3="",F3=""),"",D3-F3) -> 2910
A4: 1 | B4: 2026 | C4: =IF(OR($A4="",$B4=""),"", SUMIFS(Transactions!$D:$D, Transactions!$C:$C,"IN", Transactions!$L:$L,"Client", Transactions!$Q:$Q,"*Paid*", Transactions!$A:$A,">="&DATE($B4,$A4,1), Transactions!$A:$A,"<"&EDATE(DATE($B4,$A4,1),1) ) ) -> 63389.57 | D4: =IF(OR($A4="",$B4=""),"", SUMIFS(Transactions!$O:$O, Transactions!$C:$C,"IN", Transactions!$L:$L,"Client", Transactions!$Q:$Q,"*Paid*", Transactions!$A:$A,">="&DATE($B4,$A4,1), Transactions!$A:$A,"<"&EDATE(DATE($B4,$A4,1),1) ) ) -> 9283.44 | E4: =SUMIFS( Transactions!$D:$D, Transactions!$C:$C,"OUT", Transactions!$E:$E,"Cash", Transactions!$A:$A,">=" & DATE($B4,$A4,1), Transactions!$A:$A,"<" & DATE($B4,$A4+1,1) ) -> 57420.58 | F4: =SUMIFS( Transactions!$O:$O, Transactions!$C:$C,"OUT", Transactions!$E:$E,"Cash", Transactions!$A:$A,">=" & DATE($B4,$A4,1), Transactions!$A:$A,"<" & DATE($B4,$A4+1,1) ) -> 1507.89 | G4: =IF(OR(D4="",F4=""),"",D4-F4) -> 7775.55
A5: 2 | B5: 2026 | C5: =IF(OR($A5="",$B5=""),"", SUMIFS(Transactions!$D:$D, Transactions!$C:$C,"IN", Transactions!$L:$L,"Client", Transactions!$Q:$Q,"*Paid*", Transactions!$A:$A,">="&DATE($B5,$A5,1), Transactions!$A:$A,"<"&EDATE(DATE($B5,$A5,1),1) ) ) -> 115500 | D5: =IF(OR($A5="",$B5=""),"", SUMIFS(Transactions!$O:$O, Transactions!$C:$C,"IN", Transactions!$L:$L,"Client", Transactions!$Q:$Q,"*Paid*", Transactions!$A:$A,">="&DATE($B5,$A5,1), Transactions!$A:$A,"<"&EDATE(DATE($B5,$A5,1),1) ) ) -> 17325 | E5: =SUMIFS( Transactions!$D:$D, Transactions!$C:$C,"OUT", Transactions!$E:$E,"Cash", Transactions!$A:$A,">=" & DATE($B5,$A5,1), Transactions!$A:$A,"<" & DATE($B5,$A5+1,1) ) -> 114889.18 | F5: =SUMIFS( Transactions!$O:$O, Transactions!$C:$C,"OUT", Transactions!$E:$E,"Cash", Transactions!$A:$A,">=" & DATE($B5,$A5,1), Transactions!$A:$A,"<" & DATE($B5,$A5+1,1) ) -> 3434.54 | G5: =IF(OR(D5="",F5=""),"",D5-F5) -> 13890.46
A6: 3 | B6: 2026 | C6: =IF(OR($A6="",$B6=""),"", SUMIFS(Transactions!$D:$D, Transactions!$C:$C,"IN", Transactions!$L:$L,"Client", Transactions!$Q:$Q,"*Paid*", Transactions!$A:$A,">="&DATE($B6,$A6,1), Transactions!$A:$A,"<"&EDATE(DATE($B6,$A6,1),1) ) ) -> 83448 | D6: =IF(OR($A6="",$B6=""),"", SUMIFS(Transactions!$O:$O, Transactions!$C:$C,"IN", Transactions!$L:$L,"Client", Transactions!$Q:$Q,"*Paid*", Transactions!$A:$A,">="&DATE($B6,$A6,1), Transactions!$A:$A,"<"&EDATE(DATE($B6,$A6,1),1) ) ) -> 9831.45 | E6: =SUMIFS( Transactions!$D:$D, Transactions!$C:$C,"OUT", Transactions!$E:$E,"Cash", Transactions!$A:$A,">=" & DATE($B6,$A6,1), Transactions!$A:$A,"<" & DATE($B6,$A6+1,1) ) -> 129469.78 | F6: =SUMIFS( Transactions!$O:$O, Transactions!$C:$C,"OUT", Transactions!$E:$E,"Cash", Transactions!$A:$A,">=" & DATE($B6,$A6,1), Transactions!$A:$A,"<" & DATE($B6,$A6+1,1) ) -> 4892.25 | G6: =IF(OR(D6="",F6=""),"",D6-F6) -> 4939.2
C7: =IF(OR($A7="",$B7=""),"", SUMIFS(Transactions!$D:$D, Transactions!$C:$C,"IN", Transactions!$L:$L,"Client", Transactions!$Q:$Q,"*Paid*", Transactions!$A:$A,">="&DATE($B7,$A7,1), Transactions!$A:$A,"<"&EDATE(DATE($B7,$A7,1),1) ) ) | D7: =IF(OR($A7="",$B7=""),"", SUMIFS(Transactions!$O:$O, Transactions!$C:$C,"IN", Transactions!$L:$L,"Client", Transactions!$Q:$Q,"*Paid*", Transactions!$A:$A,">="&DATE($B7,$A7,1), Transactions!$A:$A,"<"&EDATE(DATE($B7,$A7,1),1) ) ) | E7: =SUMIFS( Transactions!$D:$D, Transactions!$C:$C,"OUT", Transactions!$E:$E,"Cash", Transactions!$A:$A,">=" & DATE($B7,$A7,1), Transactions!$A:$A,"<" & DATE($B7,$A7+1,1) ) -> 0 | F7: =SUMIFS( Transactions!$O:$O, Transactions!$C:$C,"OUT", Transactions!$E:$E,"Cash", Transactions!$A:$A,">=" & DATE($B7,$A7,1), Transactions!$A:$A,"<" & DATE($B7,$A7+1,1) ) -> 0 | G7: =IF(OR(D7="",F7=""),"",D7-F7)
C8: =IF(OR($A8="",$B8=""),"", SUMIFS(Transactions!$D:$D, Transactions!$C:$C,"IN", Transactions!$L:$L,"Client", Transactions!$Q:$Q,"*Paid*", Transactions!$A:$A,">="&DATE($B8,$A8,1), Transactions!$A:$A,"<"&EDATE(DATE($B8,$A8,1),1) ) ) | D8: =IF(OR($A8="",$B8=""),"", SUMIFS(Transactions!$O:$O, Transactions!$C:$C,"IN", Transactions!$L:$L,"Client", Transactions!$Q:$Q,"*Paid*", Transactions!$A:$A,">="&DATE($B8,$A8,1), Transactions!$A:$A,"<"&EDATE(DATE($B8,$A8,1),1) ) ) | E8: =SUMIFS( Transactions!$D:$D, Transactions!$C:$C,"OUT", Transactions!$E:$E,"Cash", Transactions!$A:$A,">=" & DATE($B8,$A8,1), Transactions!$A:$A,"<" & DATE($B8,$A8+1,1) ) -> 0 | F8: =SUMIFS( Transactions!$O:$O, Transactions!$C:$C,"OUT", Transactions!$E:$E,"Cash", Transactions!$A:$A,">=" & DATE($B8,$A8,1), Transactions!$A:$A,"<" & DATE($B8,$A8+1,1) ) -> 0 | G8: =IF(OR(D8="",F8=""),"",D8-F8)
C9: =IF(OR($A9="",$B9=""),"", SUMIFS(Transactions!$D:$D, Transactions!$C:$C,"IN", Transactions!$L:$L,"Client", Transactions!$Q:$Q,"*Paid*", Transactions!$A:$A,">="&DATE($B9,$A9,1), Transactions!$A:$A,"<"&EDATE(DATE($B9,$A9,1),1) ) ) | D9: =IF(OR($A9="",$B9=""),"", SUMIFS(Transactions!$O:$O, Transactions!$C:$C,"IN", Transactions!$L:$L,"Client", Transactions!$Q:$Q,"*Paid*", Transactions!$A:$A,">="&DATE($B9,$A9,1), Transactions!$A:$A,"<"&EDATE(DATE($B9,$A9,1),1) ) ) | E9: =SUMIFS( Transactions!$D:$D, Transactions!$C:$C,"OUT", Transactions!$E:$E,"Cash", Transactions!$A:$A,">=" & DATE($B9,$A9,1), Transactions!$A:$A,"<" & DATE($B9,$A9+1,1) ) -> 0 | F9: =SUMIFS( Transactions!$O:$O, Transactions!$C:$C,"OUT", Transactions!$E:$E,"Cash", Transactions!$A:$A,">=" & DATE($B9,$A9,1), Transactions!$A:$A,"<" & DATE($B9,$A9+1,1) ) -> 0 | G9: =IF(OR(D9="",F9=""),"",D9-F9)
C10: =IF(OR($A10="",$B10=""),"", SUMIFS(Transactions!$D:$D, Transactions!$C:$C,"IN", Transactions!$L:$L,"Client", Transactions!$Q:$Q,"*Paid*", Transactions!$A:$A,">="&DATE($B10,$A10,1), Transactions!$A:$A,"<"&EDATE(DATE($B10,$A10,1),1) ) ) | D10: =IF(OR($A10="",$B10=""),"", SUMIFS(Transactions!$O:$O, Transactions!$C:$C,"IN", Transactions!$L:$L,"Client", Transactions!$Q:$Q,"*Paid*", Transactions!$A:$A,">="&DATE($B10,$A10,1), Transactions!$A:$A,"<"&EDATE(DATE($B10,$A10,1),1) ) ) | E10: =SUMIFS( Transactions!$D:$D, Transactions!$C:$C,"OUT", Transactions!$E:$E,"Cash", Transactions!$A:$A,">=" & DATE($B10,$A10,1), Transactions!$A:$A,"<" & DATE($B10,$A10+1,1) ) -> 0 | F10: =SUMIFS( Transactions!$O:$O, Transactions!$C:$C,"OUT", Transactions!$E:$E,"Cash", Transactions!$A:$A,">=" & DATE($B10,$A10,1), Transactions!$A:$A,"<" & DATE($B10,$A10+1,1) ) -> 0 | G10: =IF(OR(D10="",F10=""),"",D10-F10)
C11: =IF(OR($A11="",$B11=""),"", SUMIFS(Transactions!$D:$D, Transactions!$C:$C,"IN", Transactions!$L:$L,"Client", Transactions!$Q:$Q,"*Paid*", Transactions!$A:$A,">="&DATE($B11,$A11,1), Transactions!$A:$A,"<"&EDATE(DATE($B11,$A11,1),1) ) ) | D11: =IF(OR($A11="",$B11=""),"", SUMIFS(Transactions!$O:$O, Transactions!$C:$C,"IN", Transactions!$L:$L,"Client", Transactions!$Q:$Q,"*Paid*", Transactions!$A:$A,">="&DATE($B11,$A11,1), Transactions!$A:$A,"<"&EDATE(DATE($B11,$A11,1),1) ) ) | E11: =SUMIFS( Transactions!$D:$D, Transactions!$C:$C,"OUT", Transactions!$E:$E,"Cash", Transactions!$A:$A,">=" & DATE($B11,$A11,1), Transactions!$A:$A,"<" & DATE($B11,$A11+1,1) ) -> 0 | F11: =SUMIFS( Transactions!$O:$O, Transactions!$C:$C,"OUT", Transactions!$E:$E,"Cash", Transactions!$A:$A,">=" & DATE($B11,$A11,1), Transactions!$A:$A,"<" & DATE($B11,$A11+1,1) ) -> 0 | G11: =IF(OR(D11="",F11=""),"",D11-F11)
C12: =IF(OR($A12="",$B12=""),"", SUMIFS(Transactions!$D:$D, Transactions!$C:$C,"IN", Transactions!$L:$L,"Client", Transactions!$Q:$Q,"*Paid*", Transactions!$A:$A,">="&DATE($B12,$A12,1), Transactions!$A:$A,"<"&EDATE(DATE($B12,$A12,1),1) ) ) | D12: =IF(OR($A12="",$B12=""),"", SUMIFS(Transactions!$O:$O, Transactions!$C:$C,"IN", Transactions!$L:$L,"Client", Transactions!$Q:$Q,"*Paid*", Transactions!$A:$A,">="&DATE($B12,$A12,1), Transactions!$A:$A,"<"&EDATE(DATE($B12,$A12,1),1) ) ) | E12: =SUMIFS( Transactions!$D:$D, Transactions!$C:$C,"OUT", Transactions!$E:$E,"Cash", Transactions!$A:$A,">=" & DATE($B12,$A12,1), Transactions!$A:$A,"<" & DATE($B12,$A12+1,1) ) -> 0 | F12: =SUMIFS( Transactions!$O:$O, Transactions!$C:$C,"OUT", Transactions!$E:$E,"Cash", Transactions!$A:$A,">=" & DATE($B12,$A12,1), Transactions!$A:$A,"<" & DATE($B12,$A12+1,1) ) -> 0 | G12: =IF(OR(D12="",F12=""),"",D12-F12)
C13: =IF(OR($A13="",$B13=""),"", SUMIFS(Transactions!$D:$D, Transactions!$C:$C,"IN", Transactions!$L:$L,"Client", Transactions!$Q:$Q,"*Paid*", Transactions!$A:$A,">="&DATE($B13,$A13,1), Transactions!$A:$A,"<"&EDATE(DATE($B13,$A13,1),1) ) ) | D13: =IF(OR($A13="",$B13=""),"", SUMIFS(Transactions!$O:$O, Transactions!$C:$C,"IN", Transactions!$L:$L,"Client", Transactions!$Q:$Q,"*Paid*", Transactions!$A:$A,">="&DATE($B13,$A13,1), Transactions!$A:$A,"<"&EDATE(DATE($B13,$A13,1),1) ) ) | E13: =SUMIFS( Transactions!$D:$D, Transactions!$C:$C,"OUT", Transactions!$E:$E,"Cash", Transactions!$A:$A,">=" & DATE($B13,$A13,1), Transactions!$A:$A,"<" & DATE($B13,$A13+1,1) ) -> 0 | F13: =SUMIFS( Transactions!$O:$O, Transactions!$C:$C,"OUT", Transactions!$E:$E,"Cash", Transactions!$A:$A,">=" & DATE($B13,$A13,1), Transactions!$A:$A,"<" & DATE($B13,$A13+1,1) ) -> 0 | G13: =IF(OR(D13="",F13=""),"",D13-F13)
C14: =IF(OR($A14="",$B14=""),"", SUMIFS(Transactions!$D:$D, Transactions!$C:$C,"IN", Transactions!$L:$L,"Client", Transactions!$Q:$Q,"*Paid*", Transactions!$A:$A,">="&DATE($B14,$A14,1), Transactions!$A:$A,"<"&EDATE(DATE($B14,$A14,1),1) ) ) | D14: =IF(OR($A14="",$B14=""),"", SUMIFS(Transactions!$O:$O, Transactions!$C:$C,"IN", Transactions!$L:$L,"Client", Transactions!$Q:$Q,"*Paid*", Transactions!$A:$A,">="&DATE($B14,$A14,1), Transactions!$A:$A,"<"&EDATE(DATE($B14,$A14,1),1) ) ) | E14: =SUMIFS( Transactions!$D:$D, Transactions!$C:$C,"OUT", Transactions!$E:$E,"Cash", Transactions!$A:$A,">=" & DATE($B14,$A14,1), Transactions!$A:$A,"<" & DATE($B14,$A14+1,1) ) -> 0 | F14: =SUMIFS( Transactions!$O:$O, Transactions!$C:$C,"OUT", Transactions!$E:$E,"Cash", Transactions!$A:$A,">=" & DATE($B14,$A14,1), Transactions!$A:$A,"<" & DATE($B14,$A14+1,1) ) -> 0 | G14: =IF(OR(D14="",F14=""),"",D14-F14)
C15: =IF(OR($A15="",$B15=""),"", SUMIFS(Transactions!$D:$D, Transactions!$C:$C,"IN", Transactions!$L:$L,"Client", Transactions!$Q:$Q,"*Paid*", Transactions!$A:$A,">="&DATE($B15,$A15,1), Transactions!$A:$A,"<"&EDATE(DATE($B15,$A15,1),1) ) ) | D15: =IF(OR($A15="",$B15=""),"", SUMIFS(Transactions!$O:$O, Transactions!$C:$C,"IN", Transactions!$L:$L,"Client", Transactions!$Q:$Q,"*Paid*", Transactions!$A:$A,">="&DATE($B15,$A15,1), Transactions!$A:$A,"<"&EDATE(DATE($B15,$A15,1),1) ) ) | E15: =SUMIFS( Transactions!$D:$D, Transactions!$C:$C,"OUT", Transactions!$E:$E,"Cash", Transactions!$A:$A,">=" & DATE($B15,$A15,1), Transactions!$A:$A,"<" & DATE($B15,$A15+1,1) ) -> 0 | F15: =SUMIFS( Transactions!$O:$O, Transactions!$C:$C,"OUT", Transactions!$E:$E,"Cash", Transactions!$A:$A,">=" & DATE($B15,$A15,1), Transactions!$A:$A,"<" & DATE($B15,$A15+1,1) ) -> 0 | G15: =IF(OR(D15="",F15=""),"",D15-F15)
C16: =IF(OR($A16="",$B16=""),"", SUMIFS(Transactions!$D:$D, Transactions!$C:$C,"IN", Transactions!$L:$L,"Client", Transactions!$Q:$Q,"*Paid*", Transactions!$A:$A,">="&DATE($B16,$A16,1), Transactions!$A:$A,"<"&EDATE(DATE($B16,$A16,1),1) ) ) | D16: =IF(OR($A16="",$B16=""),"", SUMIFS(Transactions!$O:$O, Transactions!$C:$C,"IN", Transactions!$L:$L,"Client", Transactions!$Q:$Q,"*Paid*", Transactions!$A:$A,">="&DATE($B16,$A16,1), Transactions!$A:$A,"<"&EDATE(DATE($B16,$A16,1),1) ) ) | E16: =SUMIFS( Transactions!$D:$D, Transactions!$C:$C,"OUT", Transactions!$E:$E,"Cash", Transactions!$A:$A,">=" & DATE($B16,$A16,1), Transactions!$A:$A,"<" & DATE($B16,$A16+1,1) ) -> 0 | F16: =SUMIFS( Transactions!$O:$O, Transactions!$C:$C,"OUT", Transactions!$E:$E,"Cash", Transactions!$A:$A,">=" & DATE($B16,$A16,1), Transactions!$A:$A,"<" & DATE($B16,$A16+1,1) ) -> 0 | G16: =IF(OR(D16="",F16=""),"",D16-F16)

Sheet Monthly_Report
A1: Month | B1: Year | C1: Total Income (Excl. VAT) | D1: Total Expense (Excl. VAT) | E1: Net Profit / Loss | F1: Material Expense | G1: Food Expense | H1: Fuel Expense | I1: Labour Expense | J1: Transport Expense | K1: Credit Sale
A2: 11 | B2: 2025 | C2: =SUMIFS( Transactions!$D:$D, Transactions!$C:$C,"IN", Transactions!$E:$E,"Cash", Transactions!$A:$A,">=" & DATE($B2,$A2,1), Transactions!$A:$A,"<" & EOMONTH(DATE($B2,$A2,1),0)+1 ) -> 40425 | D2: =SUMIFS( Transactions!$D:$D, Transactions!$C:$C,"OUT", Transactions!$E:$E,"Cash", Transactions!$A:$A,">="&DATE($B2,$A2,1), Transactions!$A:$A,"<"&DATE($B2,$A2+1,1) ) -> 30410.05 | E2: =C2-D2 -> 10014.95 | F2: =SUMIFS( Transactions!$D:$D, Transactions!$C:$C,"OUT", Transactions!$E:$E,"Cash", Transactions!$F:$F,"Material Purchase", Transactions!$A:$A,">="&DATE($B2,$A2,1), Transactions!$A:$A,"<"&DATE($B2,$A2+1,1) ) -> 7996.7 | G2: =SUMIFS( Transactions!$D:$D, Transactions!$C:$C,"OUT", Transactions!$E:$E,"Cash", Transactions!$F:$F,"Food Expense", Transactions!$A:$A,">="&DATE($B2,$A2,1), Transactions!$A:$A,"<"&DATE($B2,$A2+1,1) ) -> 1099.99 | H2: =SUMIFS( Transactions!$D:$D, Transactions!$C:$C,"OUT", Transactions!$E:$E,"Cash", Transactions!$F:$F,"Fuel Expense", Transactions!$A:$A,">="&DATE($B2,$A2,1), Transactions!$A:$A,"<"&DATE($B2,$A2+1,1) ) -> 840.81 | I2: =SUMIFS( Transactions!$D:$D, Transactions!$C:$C,"OUT", Transactions!$E:$E,"Cash", Transactions!$F:$F,"Labour Expense", Transactions!$A:$A,">="&DATE($B2,$A2,1), Transactions!$A:$A,"<"&DATE($B2,$A2+1,1) ) -> 7382.61 | J2: =SUMIFS( Transactions!$D:$D, Transactions!$C:$C,"OUT", Transactions!$E:$E,"Cash", Transactions!$F:$F,"Transport Expense", Transactions!$A:$A,">="&DATE($B2,$A2,1), Transactions!$A:$A,"<"&DATE($B2,$A2+1,1) ) -> 1953.04 | K2: =SUMIFS( Transactions!$D:$D, Transactions!$C:$C,"IN", Transactions!$E:$E,"Accounts Receivable", Transactions!$A:$A,">=" & DATE($B2,$A2,1), Transactions!$A:$A,"<" & EOMONTH(DATE($B2,$A2,1),0)+1 ) -> 9652.5
A3: 12 | B3: 2025 | C3: =SUMIFS( Transactions!$D:$D, Transactions!$C:$C,"IN", Transactions!$E:$E,"Cash", Transactions!$A:$A,">=" & DATE($B3,$A3,1), Transactions!$A:$A,"<" & EOMONTH(DATE($B3,$A3,1),0)+1 ) -> 67827.5 | D3: =SUMIFS( Transactions!$D:$D, Transactions!$C:$C,"OUT", Transactions!$E:$E,"Cash", Transactions!$A:$A,">="&DATE($B3,$A3,1), Transactions!$A:$A,"<"&DATE($B3,$A3+1,1) ) -> 76881.28 | E3: =C3-D3 -> -9053.78 | F3: =SUMIFS( Transactions!$D:$D, Transactions!$C:$C,"OUT", Transactions!$E:$E,"Cash", Transactions!$F:$F,"Material Purchase", Transactions!$A:$A,">="&DATE($B3,$A3,1), Transactions!$A:$A,"<"&DATE($B3,$A3+1,1) ) -> 22025.95 | G3: =SUMIFS( Transactions!$D:$D, Transactions!$C:$C,"OUT", Transactions!$E:$E,"Cash", Transactions!$F:$F,"Food Expense", Transactions!$A:$A,">="&DATE($B3,$A3,1), Transactions!$A:$A,"<"&DATE($B3,$A3+1,1) ) -> 820.56 | H3: =SUMIFS( Transactions!$D:$D, Transactions!$C:$C,"OUT", Transactions!$E:$E,"Cash", Transactions!$F:$F,"Fuel Expense", Transactions!$A:$A,">="&DATE($B3,$A3,1), Transactions!$A:$A,"<"&DATE($B3,$A3+1,1) ) -> 1559.62 | I3: =SUMIFS( Transactions!$D:$D, Transactions!$C:$C,"OUT", Transactions!$E:$E,"Cash", Transactions!$F:$F,"Labour Expense", Transactions!$A:$A,">="&DATE($B3,$A3,1), Transactions!$A:$A,"<"&DATE($B3,$A3+1,1) ) -> 3500 | J3: =SUMIFS( Transactions!$D:$D, Transactions!$C:$C,"OUT", Transactions!$E:$E,"Cash", Transactions!$F:$F,"Transport Expense", Transactions!$A:$A,">="&DATE($B3,$A3,1), Transactions!$A:$A,"<"&DATE($B3,$A3+1,1) ) -> 2430 | K3: =SUMIFS( Transactions!$D:$D, Transactions!$C:$C,"IN", Transactions!$E:$E,"Accounts Receivable", Transactions!$A:$A,">=" & DATE($B3,$A3,1), Transactions!$A:$A,"<" & EOMONTH(DATE($B3,$A3,1),0)+1 ) -> 20400
A4: 1 | B4: 2026 | C4: =SUMIFS( Transactions!$D:$D, Transactions!$C:$C,"IN", Transactions!$E:$E,"Cash", Transactions!$A:$A,">=" & DATE($B4,$A4,1), Transactions!$A:$A,"<" & EOMONTH(DATE($B4,$A4,1),0)+1 ) -> 63389.57 | D4: =SUMIFS( Transactions!$D:$D, Transactions!$C:$C,"OUT", Transactions!$E:$E,"Cash", Transactions!$A:$A,">="&DATE($B4,$A4,1), Transactions!$A:$A,"<"&DATE($B4,$A4+1,1) ) -> 57420.58 | E4: =C4-D4 -> 5968.99 | F4: =SUMIFS( Transactions!$D:$D, Transactions!$C:$C,"OUT", Transactions!$E:$E,"Cash", Transactions!$F:$F,"Material Purchase", Transactions!$A:$A,">="&DATE($B4,$A4,1), Transactions!$A:$A,"<"&DATE($B4,$A4+1,1) ) -> 7401.7 | G4: =SUMIFS( Transactions!$D:$D, Transactions!$C:$C,"OUT", Transactions!$E:$E,"Cash", Transactions!$F:$F,"Food Expense", Transactions!$A:$A,">="&DATE($B4,$A4,1), Transactions!$A:$A,"<"&DATE($B4,$A4+1,1) ) -> 1900.25 | H4: =SUMIFS( Transactions!$D:$D, Transactions!$C:$C,"OUT", Transactions!$E:$E,"Cash", Transactions!$F:$F,"Fuel Expense", Transactions!$A:$A,">="&DATE($B4,$A4,1), Transactions!$A:$A,"<"&DATE($B4,$A4+1,1) ) -> 3143.52 | I4: =SUMIFS( Transactions!$D:$D, Transactions!$C:$C,"OUT", Transactions!$E:$E,"Cash", Transactions!$F:$F,"Labour Expense", Transactions!$A:$A,">="&DATE($B4,$A4,1), Transactions!$A:$A,"<"&DATE($B4,$A4+1,1) ) -> 0 | J4: =SUMIFS( Transactions!$D:$D, Transactions!$C:$C,"OUT", Transactions!$E:$E,"Cash", Transactions!$F:$F,"Transport Expense", Transactions!$A:$A,">="&DATE($B4,$A4,1), Transactions!$A:$A,"<"&DATE($B4,$A4+1,1) ) -> 700 | K4: =SUMIFS( Transactions!$D:$D, Transactions!$C:$C,"IN", Transactions!$E:$E,"Accounts Receivable", Transactions!$A:$A,">=" & DATE($B4,$A4,1), Transactions!$A:$A,"<" & EOMONTH(DATE($B4,$A4,1),0)+1 ) -> 0
A5: 2 | B5: 2026 | C5: =SUMIFS( Transactions!$D:$D, Transactions!$C:$C,"IN", Transactions!$E:$E,"Cash", Transactions!$A:$A,">=" & DATE($B5,$A5,1), Transactions!$A:$A,"<" & EOMONTH(DATE($B5,$A5,1),0)+1 ) -> 115500 | D5: =SUMIFS( Transactions!$D:$D, Transactions!$C:$C,"OUT", Transactions!$E:$E,"Cash", Transactions!$A:$A,">="&DATE($B5,$A5,1), Transactions!$A:$A,"<"&DATE($B5,$A5+1,1) ) -> 114889.18 | E5: =C5-D5 -> 610.82 | F5: =SUMIFS( Transactions!$D:$D, Transactions!$C:$C,"OUT", Transactions!$E:$E,"Cash", Transactions!$F:$F,"Material Purchase", Transactions!$A:$A,">="&DATE($B5,$A5,1), Transactions!$A:$A,"<"&DATE($B5,$A5+1,1) ) -> 30956.22 | G5: =SUMIFS( Transactions!$D:$D, Transactions!$C:$C,"OUT", Transactions!$E:$E,"Cash", Transactions!$F:$F,"Food Expense", Transactions!$A:$A,">="&DATE($B5,$A5,1), Transactions!$A:$A,"<"&DATE($B5,$A5+1,1) ) -> 777.67 | H5: =SUMIFS( Transactions!$D:$D, Transactions!$C:$C,"OUT", Transactions!$E:$E,"Cash", Transactions!$F:$F,"Fuel Expense", Transactions!$A:$A,">="&DATE($B5,$A5,1), Transactions!$A:$A,"<"&DATE($B5,$A5+1,1) ) -> 2007.77 | I5: =SUMIFS( Transactions!$D:$D, Transactions!$C:$C,"OUT", Transactions!$E:$E,"Cash", Transactions!$F:$F,"Labour Expense", Transactions!$A:$A,">="&DATE($B5,$A5,1), Transactions!$A:$A,"<"&DATE($B5,$A5+1,1) ) -> 0 | J5: =SUMIFS( Transactions!$D:$D, Transactions!$C:$C,"OUT", Transactions!$E:$E,"Cash", Transactions!$F:$F,"Transport Expense", Transactions!$A:$A,">="&DATE($B5,$A5,1), Transactions!$A:$A,"<"&DATE($B5,$A5+1,1) ) -> 210 | K5: =SUMIFS( Transactions!$D:$D, Transactions!$C:$C,"IN", Transactions!$E:$E,"Accounts Receivable", Transactions!$A:$A,">=" & DATE($B5,$A5,1), Transactions!$A:$A,"<" & EOMONTH(DATE($B5,$A5,1),0)+1 ) -> 0
A6: 3 | B6: 2026 | C6: =SUMIFS( Transactions!$D:$D, Transactions!$C:$C,"IN", Transactions!$E:$E,"Cash", Transactions!$A:$A,">=" & DATE($B6,$A6,1), Transactions!$A:$A,"<" & EOMONTH(DATE($B6,$A6,1),0)+1 ) -> 83448 | D6: =SUMIFS( Transactions!$D:$D, Transactions!$C:$C,"OUT", Transactions!$E:$E,"Cash", Transactions!$A:$A,">="&DATE($B6,$A6,1), Transactions!$A:$A,"<"&DATE($B6,$A6+1,1) ) -> 129469.78 | E6: =C6-D6 -> -46021.78 | F6: =SUMIFS( Transactions!$D:$D, Transactions!$C:$C,"OUT", Transactions!$E:$E,"Cash", Transactions!$F:$F,"Material Purchase", Transactions!$A:$A,">="&DATE($B6,$A6,1), Transactions!$A:$A,"<"&DATE($B6,$A6+1,1) ) -> 14847.36 | G6: =SUMIFS( Transactions!$D:$D, Transactions!$C:$C,"OUT", Transactions!$E:$E,"Cash", Transactions!$F:$F,"Food Expense", Transactions!$A:$A,">="&DATE($B6,$A6,1), Transactions!$A:$A,"<"&DATE($B6,$A6+1,1) ) -> 2317.89 | H6: =SUMIFS( Transactions!$D:$D, Transactions!$C:$C,"OUT", Transactions!$E:$E,"Cash", Transactions!$F:$F,"Fuel Expense", Transactions!$A:$A,">="&DATE($B6,$A6,1), Transactions!$A:$A,"<"&DATE($B6,$A6+1,1) ) -> 2328.09 | I6: =SUMIFS( Transactions!$D:$D, Transactions!$C:$C,"OUT", Transactions!$E:$E,"Cash", Transactions!$F:$F,"Labour Expense", Transactions!$A:$A,">="&DATE($B6,$A6,1), Transactions!$A:$A,"<"&DATE($B6,$A6+1,1) ) -> 0 | J6: =SUMIFS( Transactions!$D:$D, Transactions!$C:$C,"OUT", Transactions!$E:$E,"Cash", Transactions!$F:$F,"Transport Expense", Transactions!$A:$A,">="&DATE($B6,$A6,1), Transactions!$A:$A,"<"&DATE($B6,$A6+1,1) ) -> 600 | K6: =SUMIFS( Transactions!$D:$D, Transactions!$C:$C,"IN", Transactions!$E:$E,"Accounts Receivable", Transactions!$A:$A,">=" & DATE($B6,$A6,1), Transactions!$A:$A,"<" & EOMONTH(DATE($B6,$A6,1),0)+1 ) -> 0
C7: =SUMIFS( Transactions!$D:$D, Transactions!$C:$C,"IN", Transactions!$E:$E,"Cash", Transactions!$A:$A,">=" & DATE($B7,$A7,1), Transactions!$A:$A,"<" & EOMONTH(DATE($B7,$A7,1),0)+1 ) -> 0 | D7: =SUMIFS( Transactions!$D:$D, Transactions!$C:$C,"OUT", Transactions!$E:$E,"Cash", Transactions!$A:$A,">="&DATE($B7,$A7,1), Transactions!$A:$A,"<"&DATE($B7,$A7+1,1) ) -> 0 | E7: =C7-D7 -> 0 | F7: =SUMIFS( Transactions!$D:$D, Transactions!$C:$C,"OUT", Transactions!$E:$E,"Cash", Transactions!$F:$F,"Material Purchase", Transactions!$A:$A,">="&DATE($B7,$A7,1), Transactions!$A:$A,"<"&DATE($B7,$A7+1,1) ) -> 0 | G7: =SUMIFS( Transactions!$D:$D, Transactions!$C:$C,"OUT", Transactions!$E:$E,"Cash", Transactions!$F:$F,"Food Expense", Transactions!$A:$A,">="&DATE($B7,$A7,1), Transactions!$A:$A,"<"&DATE($B7,$A7+1,1) ) -> 0 | H7: =SUMIFS( Transactions!$D:$D, Transactions!$C:$C,"OUT", Transactions!$E:$E,"Cash", Transactions!$F:$F,"Fuel Expense", Transactions!$A:$A,">="&DATE($B7,$A7,1), Transactions!$A:$A,"<"&DATE($B7,$A7+1,1) ) -> 0 | I7: =SUMIFS( Transactions!$D:$D, Transactions!$C:$C,"OUT", Transactions!$E:$E,"Cash", Transactions!$F:$F,"Labour Expense", Transactions!$A:$A,">="&DATE($B7,$A7,1), Transactions!$A:$A,"<"&DATE($B7,$A7+1,1) ) -> 0 | J7: =SUMIFS( Transactions!$D:$D, Transactions!$C:$C,"OUT", Transactions!$E:$E,"Cash", Transactions!$F:$F,"Transport Expense", Transactions!$A:$A,">="&DATE($B7,$A7,1), Transactions!$A:$A,"<"&DATE($B7,$A7+1,1) ) -> 0 | K7: =SUMIFS( Transactions!$D:$D, Transactions!$C:$C,"IN", Transactions!$E:$E,"Accounts Receivable", Transactions!$A:$A,">=" & DATE($B7,$A7,1), Transactions!$A:$A,"<" & EOMONTH(DATE($B7,$A7,1),0)+1 ) -> 0
C8: =SUMIFS( Transactions!$D:$D, Transactions!$C:$C,"IN", Transactions!$E:$E,"Cash", Transactions!$A:$A,">=" & DATE($B8,$A8,1), Transactions!$A:$A,"<" & EOMONTH(DATE($B8,$A8,1),0)+1 ) -> 0 | D8: =SUMIFS( Transactions!$D:$D, Transactions!$C:$C,"OUT", Transactions!$E:$E,"Cash", Transactions!$A:$A,">="&DATE($B8,$A8,1), Transactions!$A:$A,"<"&DATE($B8,$A8+1,1) ) -> 0 | E8: =C8-D8 -> 0 | F8: =SUMIFS( Transactions!$D:$D, Transactions!$C:$C,"OUT", Transactions!$E:$E,"Cash", Transactions!$F:$F,"Material Purchase", Transactions!$A:$A,">="&DATE($B8,$A8,1), Transactions!$A:$A,"<"&DATE($B8,$A8+1,1) ) -> 0 | G8: =SUMIFS( Transactions!$D:$D, Transactions!$C:$C,"OUT", Transactions!$E:$E,"Cash", Transactions!$F:$F,"Food Expense", Transactions!$A:$A,">="&DATE($B8,$A8,1), Transactions!$A:$A,"<"&DATE($B8,$A8+1,1) ) -> 0 | H8: =SUMIFS( Transactions!$D:$D, Transactions!$C:$C,"OUT", Transactions!$E:$E,"Cash", Transactions!$F:$F,"Fuel Expense", Transactions!$A:$A,">="&DATE($B8,$A8,1), Transactions!$A:$A,"<"&DATE($B8,$A8+1,1) ) -> 0 | I8: =SUMIFS( Transactions!$D:$D, Transactions!$C:$C,"OUT", Transactions!$E:$E,"Cash", Transactions!$F:$F,"Labour Expense", Transactions!$A:$A,">="&DATE($B8,$A8,1), Transactions!$A:$A,"<"&DATE($B8,$A8+1,1) ) -> 0 | J8: =SUMIFS( Transactions!$D:$D, Transactions!$C:$C,"OUT", Transactions!$E:$E,"Cash", Transactions!$F:$F,"Transport Expense", Transactions!$A:$A,">="&DATE($B8,$A8,1), Transactions!$A:$A,"<"&DATE($B8,$A8+1,1) ) -> 0 | K8: =SUMIFS( Transactions!$D:$D, Transactions!$C:$C,"IN", Transactions!$E:$E,"Accounts Receivable", Transactions!$A:$A,">=" & DATE($B8,$A8,1), Transactions!$A:$A,"<" & EOMONTH(DATE($B8,$A8,1),0)+1 ) -> 0
C9: =SUMIFS( Transactions!$D:$D, Transactions!$C:$C,"IN", Transactions!$E:$E,"Cash", Transactions!$A:$A,">=" & DATE($B9,$A9,1), Transactions!$A:$A,"<" & EOMONTH(DATE($B9,$A9,1),0)+1 ) -> 0 | D9: =SUMIFS( Transactions!$D:$D, Transactions!$C:$C,"OUT", Transactions!$E:$E,"Cash", Transactions!$A:$A,">="&DATE($B9,$A9,1), Transactions!$A:$A,"<"&DATE($B9,$A9+1,1) ) -> 0 | E9: =C9-D9 -> 0 | F9: =SUMIFS( Transactions!$D:$D, Transactions!$C:$C,"OUT", Transactions!$E:$E,"Cash", Transactions!$F:$F,"Material Purchase", Transactions!$A:$A,">="&DATE($B9,$A9,1), Transactions!$A:$A,"<"&DATE($B9,$A9+1,1) ) -> 0 | G9: =SUMIFS( Transactions!$D:$D, Transactions!$C:$C,"OUT", Transactions!$E:$E,"Cash", Transactions!$F:$F,"Food Expense", Transactions!$A:$A,">="&DATE($B9,$A9,1), Transactions!$A:$A,"<"&DATE($B9,$A9+1,1) ) -> 0 | H9: =SUMIFS( Transactions!$D:$D, Transactions!$C:$C,"OUT", Transactions!$E:$E,"Cash", Transactions!$F:$F,"Fuel Expense", Transactions!$A:$A,">="&DATE($B9,$A9,1), Transactions!$A:$A,"<"&DATE($B9,$A9+1,1) ) -> 0 | I9: =SUMIFS( Transactions!$D:$D, Transactions!$C:$C,"OUT", Transactions!$E:$E,"Cash", Transactions!$F:$F,"Labour Expense", Transactions!$A:$A,">="&DATE($B9,$A9,1), Transactions!$A:$A,"<"&DATE($B9,$A9+1,1) ) -> 0 | J9: =SUMIFS( Transactions!$D:$D, Transactions!$C:$C,"OUT", Transactions!$E:$E,"Cash", Transactions!$F:$F,"Transport Expense", Transactions!$A:$A,">="&DATE($B9,$A9,1), Transactions!$A:$A,"<"&DATE($B9,$A9+1,1) ) -> 0 | K9: =SUMIFS( Transactions!$D:$D, Transactions!$C:$C,"IN", Transactions!$E:$E,"Accounts Receivable", Transactions!$A:$A,">=" & DATE($B9,$A9,1), Transactions!$A:$A,"<" & EOMONTH(DATE($B9,$A9,1),0)+1 ) -> 0
C10: =SUMIFS( Transactions!$D:$D, Transactions!$C:$C,"IN", Transactions!$E:$E,"Cash", Transactions!$A:$A,">=" & DATE($B10,$A10,1), Transactions!$A:$A,"<" & EOMONTH(DATE($B10,$A10,1),0)+1 ) -> 0 | D10: =SUMIFS( Transactions!$D:$D, Transactions!$C:$C,"OUT", Transactions!$E:$E,"Cash", Transactions!$A:$A,">="&DATE($B10,$A10,1), Transactions!$A:$A,"<"&DATE($B10,$A10+1,1) ) -> 0 | E10: =C10-D10 -> 0 | F10: =SUMIFS( Transactions!$D:$D, Transactions!$C:$C,"OUT", Transactions!$E:$E,"Cash", Transactions!$F:$F,"Material Purchase", Transactions!$A:$A,">="&DATE($B10,$A10,1), Transactions!$A:$A,"<"&DATE($B10,$A10+1,1) ) -> 0 | G10: =SUMIFS( Transactions!$D:$D, Transactions!$C:$C,"OUT", Transactions!$E:$E,"Cash", Transactions!$F:$F,"Food Expense", Transactions!$A:$A,">="&DATE($B10,$A10,1), Transactions!$A:$A,"<"&DATE($B10,$A10+1,1) ) -> 0 | H10: =SUMIFS( Transactions!$D:$D, Transactions!$C:$C,"OUT", Transactions!$E:$E,"Cash", Transactions!$F:$F,"Fuel Expense", Transactions!$A:$A,">="&DATE($B10,$A10,1), Transactions!$A:$A,"<"&DATE($B10,$A10+1,1) ) -> 0 | I10: =SUMIFS( Transactions!$D:$D, Transactions!$C:$C,"OUT", Transactions!$E:$E,"Cash", Transactions!$F:$F,"Labour Expense", Transactions!$A:$A,">="&DATE($B10,$A10,1), Transactions!$A:$A,"<"&DATE($B10,$A10+1,1) ) -> 0 | J10: =SUMIFS( Transactions!$D:$D, Transactions!$C:$C,"OUT", Transactions!$E:$E,"Cash", Transactions!$F:$F,"Transport Expense", Transactions!$A:$A,">="&DATE($B10,$A10,1), Transactions!$A:$A,"<"&DATE($B10,$A10+1,1) ) -> 0 | K10: =SUMIFS( Transactions!$D:$D, Transactions!$C:$C,"IN", Transactions!$E:$E,"Accounts Receivable", Transactions!$A:$A,">=" & DATE($B10,$A10,1), Transactions!$A:$A,"<" & EOMONTH(DATE($B10,$A10,1),0)+1 ) -> 0
C11: =SUMIFS( Transactions!$D:$D, Transactions!$C:$C,"IN", Transactions!$E:$E,"Cash", Transactions!$A:$A,">=" & DATE($B11,$A11,1), Transactions!$A:$A,"<" & EOMONTH(DATE($B11,$A11,1),0)+1 ) -> 0 | D11: =SUMIFS( Transactions!$D:$D, Transactions!$C:$C,"OUT", Transactions!$E:$E,"Cash", Transactions!$A:$A,">="&DATE($B11,$A11,1), Transactions!$A:$A,"<"&DATE($B11,$A11+1,1) ) -> 0 | E11: =C11-D11 -> 0 | F11: =SUMIFS( Transactions!$D:$D, Transactions!$C:$C,"OUT", Transactions!$E:$E,"Cash", Transactions!$F:$F,"Material Purchase", Transactions!$A:$A,">="&DATE($B11,$A11,1), Transactions!$A:$A,"<"&DATE($B11,$A11+1,1) ) -> 0 | G11: =SUMIFS( Transactions!$D:$D, Transactions!$C:$C,"OUT", Transactions!$E:$E,"Cash", Transactions!$F:$F,"Food Expense", Transactions!$A:$A,">="&DATE($B11,$A11,1), Transactions!$A:$A,"<"&DATE($B11,$A11+1,1) ) -> 0 | H11: =SUMIFS( Transactions!$D:$D, Transactions!$C:$C,"OUT", Transactions!$E:$E,"Cash", Transactions!$F:$F,"Fuel Expense", Transactions!$A:$A,">="&DATE($B11,$A11,1), Transactions!$A:$A,"<"&DATE($B11,$A11+1,1) ) -> 0 | I11: =SUMIFS( Transactions!$D:$D, Transactions!$C:$C,"OUT", Transactions!$E:$E,"Cash", Transactions!$F:$F,"Labour Expense", Transactions!$A:$A,">="&DATE($B11,$A11,1), Transactions!$A:$A,"<"&DATE($B11,$A11+1,1) ) -> 0 | J11: =SUMIFS( Transactions!$D:$D, Transactions!$C:$C,"OUT", Transactions!$E:$E,"Cash", Transactions!$F:$F,"Transport Expense", Transactions!$A:$A,">="&DATE($B11,$A11,1), Transactions!$A:$A,"<"&DATE($B11,$A11+1,1) ) -> 0 | K11: =SUMIFS( Transactions!$D:$D, Transactions!$C:$C,"IN", Transactions!$E:$E,"Accounts Receivable", Transactions!$A:$A,">=" & DATE($B11,$A11,1), Transactions!$A:$A,"<" & EOMONTH(DATE($B11,$A11,1),0)+1 ) -> 0
C12: =SUMIFS( Transactions!$D:$D, Transactions!$C:$C,"IN", Transactions!$E:$E,"Cash", Transactions!$A:$A,">=" & DATE($B12,$A12,1), Transactions!$A:$A,"<" & EOMONTH(DATE($B12,$A12,1),0)+1 ) -> 0 | D12: =SUMIFS( Transactions!$D:$D, Transactions!$C:$C,"OUT", Transactions!$E:$E,"Cash", Transactions!$A:$A,">="&DATE($B12,$A12,1), Transactions!$A:$A,"<"&DATE($B12,$A12+1,1) ) -> 0 | E12: =C12-D12 -> 0 | F12: =SUMIFS( Transactions!$D:$D, Transactions!$C:$C,"OUT", Transactions!$E:$E,"Cash", Transactions!$F:$F,"Material Purchase", Transactions!$A:$A,">="&DATE($B12,$A12,1), Transactions!$A:$A,"<"&DATE($B12,$A12+1,1) ) -> 0 | G12: =SUMIFS( Transactions!$D:$D, Transactions!$C:$C,"OUT", Transactions!$E:$E,"Cash", Transactions!$F:$F,"Food Expense", Transactions!$A:$A,">="&DATE($B12,$A12,1), Transactions!$A:$A,"<"&DATE($B12,$A12+1,1) ) -> 0 | H12: =SUMIFS( Transactions!$D:$D, Transactions!$C:$C,"OUT", Transactions!$E:$E,"Cash", Transactions!$F:$F,"Fuel Expense", Transactions!$A:$A,">="&DATE($B12,$A12,1), Transactions!$A:$A,"<"&DATE($B12,$A12+1,1) ) -> 0 | I12: =SUMIFS( Transactions!$D:$D, Transactions!$C:$C,"OUT", Transactions!$E:$E,"Cash", Transactions!$F:$F,"Labour Expense", Transactions!$A:$A,">="&DATE($B12,$A12,1), Transactions!$A:$A,"<"&DATE($B12,$A12+1,1) ) -> 0 | J12: =SUMIFS( Transactions!$D:$D, Transactions!$C:$C,"OUT", Transactions!$E:$E,"Cash", Transactions!$F:$F,"Transport Expense", Transactions!$A:$A,">="&DATE($B12,$A12,1), Transactions!$A:$A,"<"&DATE($B12,$A12+1,1) ) -> 0 | K12: =SUMIFS( Transactions!$D:$D, Transactions!$C:$C,"IN", Transactions!$E:$E,"Accounts Receivable", Transactions!$A:$A,">=" & DATE($B12,$A12,1), Transactions!$A:$A,"<" & EOMONTH(DATE($B12,$A12,1),0)+1 ) -> 0
C13: =SUMIFS( Transactions!$D:$D, Transactions!$C:$C,"IN", Transactions!$E:$E,"Cash", Transactions!$A:$A,">=" & DATE($B13,$A13,1), Transactions!$A:$A,"<" & EOMONTH(DATE($B13,$A13,1),0)+1 ) -> 0 | D13: =SUMIFS( Transactions!$D:$D, Transactions!$C:$C,"OUT", Transactions!$E:$E,"Cash", Transactions!$A:$A,">="&DATE($B13,$A13,1), Transactions!$A:$A,"<"&DATE($B13,$A13+1,1) ) -> 0 | E13: =C13-D13 -> 0 | F13: =SUMIFS( Transactions!$D:$D, Transactions!$C:$C,"OUT", Transactions!$E:$E,"Cash", Transactions!$F:$F,"Material Purchase", Transactions!$A:$A,">="&DATE($B13,$A13,1), Transactions!$A:$A,"<"&DATE($B13,$A13+1,1) ) -> 0 | G13: =SUMIFS( Transactions!$D:$D, Transactions!$C:$C,"OUT", Transactions!$E:$E,"Cash", Transactions!$F:$F,"Food Expense", Transactions!$A:$A,">="&DATE($B13,$A13,1), Transactions!$A:$A,"<"&DATE($B13,$A13+1,1) ) -> 0 | H13: =SUMIFS( Transactions!$D:$D, Transactions!$C:$C,"OUT", Transactions!$E:$E,"Cash", Transactions!$F:$F,"Fuel Expense", Transactions!$A:$A,">="&DATE($B13,$A13,1), Transactions!$A:$A,"<"&DATE($B13,$A13+1,1) ) -> 0 | I13: =SUMIFS( Transactions!$D:$D, Transactions!$C:$C,"OUT", Transactions!$E:$E,"Cash", Transactions!$F:$F,"Labour Expense", Transactions!$A:$A,">="&DATE($B13,$A13,1), Transactions!$A:$A,"<"&DATE($B13,$A13+1,1) ) -> 0 | J13: =SUMIFS( Transactions!$D:$D, Transactions!$C:$C,"OUT", Transactions!$E:$E,"Cash", Transactions!$F:$F,"Transport Expense", Transactions!$A:$A,">="&DATE($B13,$A13,1), Transactions!$A:$A,"<"&DATE($B13,$A13+1,1) ) -> 0 | K13: =SUMIFS( Transactions!$D:$D, Transactions!$C:$C,"IN", Transactions!$E:$E,"Accounts Receivable", Transactions!$A:$A,">=" & DATE($B13,$A13,1), Transactions!$A:$A,"<" & EOMONTH(DATE($B13,$A13,1),0)+1 ) -> 0
C14: =SUMIFS( Transactions!$D:$D, Transactions!$C:$C,"IN", Transactions!$E:$E,"Cash", Transactions!$A:$A,">=" & DATE($B14,$A14,1), Transactions!$A:$A,"<" & EOMONTH(DATE($B14,$A14,1),0)+1 ) -> 0 | D14: =SUMIFS( Transactions!$D:$D, Transactions!$C:$C,"OUT", Transactions!$E:$E,"Cash", Transactions!$A:$A,">="&DATE($B14,$A14,1), Transactions!$A:$A,"<"&DATE($B14,$A14+1,1) ) -> 0 | E14: =C14-D14 -> 0 | F14: =SUMIFS( Transactions!$D:$D, Transactions!$C:$C,"OUT", Transactions!$E:$E,"Cash", Transactions!$F:$F,"Material Purchase", Transactions!$A:$A,">="&DATE($B14,$A14,1), Transactions!$A:$A,"<"&DATE($B14,$A14+1,1) ) -> 0 | G14: =SUMIFS( Transactions!$D:$D, Transactions!$C:$C,"OUT", Transactions!$E:$E,"Cash", Transactions!$F:$F,"Food Expense", Transactions!$A:$A,">="&DATE($B14,$A14,1), Transactions!$A:$A,"<"&DATE($B14,$A14+1,1) ) -> 0 | H14: =SUMIFS( Transactions!$D:$D, Transactions!$C:$C,"OUT", Transactions!$E:$E,"Cash", Transactions!$F:$F,"Fuel Expense", Transactions!$A:$A,">="&DATE($B14,$A14,1), Transactions!$A:$A,"<"&DATE($B14,$A14+1,1) ) -> 0 | I14: =SUMIFS( Transactions!$D:$D, Transactions!$C:$C,"OUT", Transactions!$E:$E,"Cash", Transactions!$F:$F,"Labour Expense", Transactions!$A:$A,">="&DATE($B14,$A14,1), Transactions!$A:$A,"<"&DATE($B14,$A14+1,1) ) -> 0 | J14: =SUMIFS( Transactions!$D:$D, Transactions!$C:$C,"OUT", Transactions!$E:$E,"Cash", Transactions!$F:$F,"Transport Expense", Transactions!$A:$A,">="&DATE($B14,$A14,1), Transactions!$A:$A,"<"&DATE($B14,$A14+1,1) ) -> 0 | K14: =SUMIFS( Transactions!$D:$D, Transactions!$C:$C,"IN", Transactions!$E:$E,"Accounts Receivable", Transactions!$A:$A,">=" & DATE($B14,$A14,1), Transactions!$A:$A,"<" & EOMONTH(DATE($B14,$A14,1),0)+1 ) -> 0
C15: =SUMIFS( Transactions!$D:$D, Transactions!$C:$C,"IN", Transactions!$E:$E,"Cash", Transactions!$A:$A,">=" & DATE($B15,$A15,1), Transactions!$A:$A,"<" & EOMONTH(DATE($B15,$A15,1),0)+1 ) -> 0 | D15: =SUMIFS( Transactions!$D:$D, Transactions!$C:$C,"OUT", Transactions!$E:$E,"Cash", Transactions!$A:$A,">="&DATE($B15,$A15,1), Transactions!$A:$A,"<"&DATE($B15,$A15+1,1) ) -> 0 | E15: =C15-D15 -> 0 | F15: =SUMIFS( Transactions!$D:$D, Transactions!$C:$C,"OUT", Transactions!$E:$E,"Cash", Transactions!$F:$F,"Material Purchase", Transactions!$A:$A,">="&DATE($B15,$A15,1), Transactions!$A:$A,"<"&DATE($B15,$A15+1,1) ) -> 0 | G15: =SUMIFS( Transactions!$D:$D, Transactions!$C:$C,"OUT", Transactions!$E:$E,"Cash", Transactions!$F:$F,"Food Expense", Transactions!$A:$A,">="&DATE($B15,$A15,1), Transactions!$A:$A,"<"&DATE($B15,$A15+1,1) ) -> 0 | H15: =SUMIFS( Transactions!$D:$D, Transactions!$C:$C,"OUT", Transactions!$E:$E,"Cash", Transactions!$F:$F,"Fuel Expense", Transactions!$A:$A,">="&DATE($B15,$A15,1), Transactions!$A:$A,"<"&DATE($B15,$A15+1,1) ) -> 0 | I15: =SUMIFS( Transactions!$D:$D, Transactions!$C:$C,"OUT", Transactions!$E:$E,"Cash", Transactions!$F:$F,"Labour Expense", Transactions!$A:$A,">="&DATE($B15,$A15,1), Transactions!$A:$A,"<"&DATE($B15,$A15+1,1) ) -> 0 | J15: =SUMIFS( Transactions!$D:$D, Transactions!$C:$C,"OUT", Transactions!$E:$E,"Cash", Transactions!$F:$F,"Transport Expense", Transactions!$A:$A,">="&DATE($B15,$A15,1), Transactions!$A:$A,"<"&DATE($B15,$A15+1,1) ) -> 0 | K15: =SUMIFS( Transactions!$D:$D, Transactions!$C:$C,"IN", Transactions!$E:$E,"Accounts Receivable", Transactions!$A:$A,">=" & DATE($B15,$A15,1), Transactions!$A:$A,"<" & EOMONTH(DATE($B15,$A15,1),0)+1 ) -> 0
C16: =SUMIFS( Transactions!$D:$D, Transactions!$C:$C,"IN", Transactions!$E:$E,"Cash", Transactions!$A:$A,">=" & DATE($B16,$A16,1), Transactions!$A:$A,"<" & EOMONTH(DATE($B16,$A16,1),0)+1 ) -> 0 | D16: =SUMIFS( Transactions!$D:$D, Transactions!$C:$C,"OUT", Transactions!$E:$E,"Cash", Transactions!$A:$A,">="&DATE($B16,$A16,1), Transactions!$A:$A,"<"&DATE($B16,$A16+1,1) ) -> 0 | E16: =C16-D16 -> 0 | F16: =SUMIFS( Transactions!$D:$D, Transactions!$C:$C,"OUT", Transactions!$E:$E,"Cash", Transactions!$F:$F,"Material Purchase", Transactions!$A:$A,">="&DATE($B16,$A16,1), Transactions!$A:$A,"<"&DATE($B16,$A16+1,1) ) -> 0 | G16: =SUMIFS( Transactions!$D:$D, Transactions!$C:$C,"OUT", Transactions!$E:$E,"Cash", Transactions!$F:$F,"Food Expense", Transactions!$A:$A,">="&DATE($B16,$A16,1), Transactions!$A:$A,"<"&DATE($B16,$A16+1,1) ) -> 0 | H16: =SUMIFS( Transactions!$D:$D, Transactions!$C:$C,"OUT", Transactions!$E:$E,"Cash", Transactions!$F:$F,"Fuel Expense", Transactions!$A:$A,">="&DATE($B16,$A16,1), Transactions!$A:$A,"<"&DATE($B16,$A16+1,1) ) -> 0 | I16: =SUMIFS( Transactions!$D:$D, Transactions!$C:$C,"OUT", Transactions!$E:$E,"Cash", Transactions!$F:$F,"Labour Expense", Transactions!$A:$A,">="&DATE($B16,$A16,1), Transactions!$A:$A,"<"&DATE($B16,$A16+1,1) ) -> 0 | J16: =SUMIFS( Transactions!$D:$D, Transactions!$C:$C,"OUT", Transactions!$E:$E,"Cash", Transactions!$F:$F,"Transport Expense", Transactions!$A:$A,">="&DATE($B16,$A16,1), Transactions!$A:$A,"<"&DATE($B16,$A16+1,1) ) -> 0 | K16: =SUMIFS( Transactions!$D:$D, Transactions!$C:$C,"IN", Transactions!$E:$E,"Accounts Receivable", Transactions!$A:$A,">=" & DATE($B16,$A16,1), Transactions!$A:$A,"<" & EOMONTH(DATE($B16,$A16,1),0)+1 ) -> 0
C17: =SUMIFS( Transactions!$D:$D, Transactions!$C:$C,"IN", Transactions!$E:$E,"Cash", Transactions!$A:$A,">=" & DATE($B17,$A17,1), Transactions!$A:$A,"<" & EOMONTH(DATE($B17,$A17,1),0)+1 ) -> 0 | D17: =SUMIFS( Transactions!$D:$D, Transactions!$C:$C,"OUT", Transactions!$E:$E,"Cash", Transactions!$A:$A,">="&DATE($B17,$A17,1), Transactions!$A:$A,"<"&DATE($B17,$A17+1,1) ) -> 0 | E17: =C17-D17 -> 0 | F17: =SUMIFS( Transactions!$D:$D, Transactions!$C:$C,"OUT", Transactions!$E:$E,"Cash", Transactions!$F:$F,"Material Purchase", Transactions!$A:$A,">="&DATE($B17,$A17,1), Transactions!$A:$A,"<"&DATE($B17,$A17+1,1) ) -> 0 | G17: =SUMIFS( Transactions!$D:$D, Transactions!$C:$C,"OUT", Transactions!$E:$E,"Cash", Transactions!$F:$F,"Food Expense", Transactions!$A:$A,">="&DATE($B17,$A17,1), Transactions!$A:$A,"<"&DATE($B17,$A17+1,1) ) -> 0 | H17: =SUMIFS( Transactions!$D:$D, Transactions!$C:$C,"OUT", Transactions!$E:$E,"Cash", Transactions!$F:$F,"Fuel Expense", Transactions!$A:$A,">="&DATE($B17,$A17,1), Transactions!$A:$A,"<"&DATE($B17,$A17+1,1) ) -> 0 | I17: =SUMIFS( Transactions!$D:$D, Transactions!$C:$C,"OUT", Transactions!$E:$E,"Cash", Transactions!$F:$F,"Labour Expense", Transactions!$A:$A,">="&DATE($B17,$A17,1), Transactions!$A:$A,"<"&DATE($B17,$A17+1,1) ) -> 0 | J17: =SUMIFS( Transactions!$D:$D, Transactions!$C:$C,"OUT", Transactions!$E:$E,"Cash", Transactions!$F:$F,"Transport Expense", Transactions!$A:$A,">="&DATE($B17,$A17,1), Transactions!$A:$A,"<"&DATE($B17,$A17+1,1) ) -> 0 | K17: =SUMIFS( Transactions!$D:$D, Transactions!$C:$C,"IN", Transactions!$E:$E,"Accounts Receivable", Transactions!$A:$A,">=" & DATE($B17,$A17,1), Transactions!$A:$A,"<" & EOMONTH(DATE($B17,$A17,1),0)+1 ) -> 0

Sheet Employees
A1: Employee Name | B1: Type (Monthly/Daily) | C1: Monthly Salary | D1: Daily Rate | E1: Days Worked (This Month) | F1: Salary Due This Month | G1: Total Salary Paid This Month | H1: Pending Salary This Month | I1: Total Advance Taken | J1: Total Advance Adjusted | K1: Advance Balance | L1: Previous Pending Salary | M1: Total Pending Salary(All Months) | N1: Note
A2: Shoaib Umar | B2: Monthly | C2: 1800 | E2: 19 | F2: =IFERROR( IF(B2="Monthly", C2, IF(B2="Daily", D2*E2, IF(B2="Weekly", C2, 0 ) ) ), 0) -> 1800 | G2: 1800 | H2: =IFERROR(IF(F2="",0,F2-G2),0) -> 0 | K2: =IFERROR(IF(I2="",0,I2-J2),0) -> 0 | L2: 1800 | M2: =IFERROR(H2+L2,0) -> 1800 | N2: Running Month 15-11-2025 to 15-12-2025
A3: Shahid | B3: Monthly | C3: 4560 | F3: =IFERROR( IF(B3="Monthly", C3, IF(B3="Daily", D3*E3, IF(B3="Weekly", C3, 0 ) ) ), 0) -> 4560 | G3: 4060 | H3: =IFERROR(IF(F3="",0,F3-G3),0) -> 500 | K3: =IFERROR(IF(I3="",0,I3-J3),0) -> 0 | M3: =IFERROR(H3+L3,0) -> 500 | N3: 1500+1500+1060 Last payment on 09/12/2025
A4: Abdullah | B4: Monthly | F4: =IFERROR( IF(B4="Monthly", C4, IF(B4="Daily", D4*E4, IF(B4="Weekly", C4, 0 ) ) ), 0) -> 0 | H4: =IFERROR(IF(F4="",0,F4-G4),0) -> 0 | K4: =IFERROR(IF(I4="",0,I4-J4),0) -> 0 | M4: =IFERROR(H4+L4,0) -> 0
A5: Yamin | B5: Monthly | F5: =IFERROR( IF(B5="Monthly", C5, IF(B5="Daily", D5*E5, IF(B5="Weekly", C5, 0 ) ) ), 0) -> 0 | H5: =IFERROR(IF(F5="",0,F5-G5),0) -> 0 | K5: =IFERROR(IF(I5="",0,I5-J5),0) -> 0 | M5: =IFERROR(H5+L5,0) -> 0
A6: Yasir Shah | B6: Weekly | F6: =IFERROR( IF(B6="Monthly", C6, IF(B6="Daily", D6*E6, IF(B6="Weekly", C6, 0 ) ) ), 0) -> 0 | G6: 306 | H6: =IFERROR(IF(F6="",0,F6-G6),0) -> -306 | K6: =IFERROR(IF(I6="",0,I6-J6),0) -> 0 | M6: =IFERROR(H6+L6,0) -> -306
G7: 2850 Tickets+2000+1500 on 09/12/25 2500 more
G8: 18+200+500+200+175+250 (1343-1037= 306) pending on yasir shah Before travel to pakistan

Sheet Dashboard
A1: Metric | B1: Value
A2: Total Cash Balance | B2: =Accounts_Summary!D2 -> -16219.5
A3: Total Bank Balance | B3: =Accounts_Summary!D3 -> 0
A4: Total Owner Net Drawings | B4: =Accounts_Summary!D4-Accounts_Summary!D5 -> 35145
A5: Total Accounts Receivable | B5: =Accounts_Summary!D6 -> 12100
A6: Total Accounts Payable (Suppliers) | B6: =Accounts_Summary!D7 -> -5600
A7: Total Employee Payable | B7: =Accounts_Summary!D8 -> 0
A8: Total Employee Advance | B8: =Accounts_Summary!D9 -> -17486
A9: Total Net Profit (All Projects) | B9: =SUM(Projects!I2:I1000) -> 256267.79
A10: Latest Month Net VAT Payable (row 2) | B10: ='Tax Report'!G2 -> 2125.89

Sheet Old Accounts Payable
A1: Suppliars Names | B1: Total payable | C1: Total paid | D1: Total Remain after Paid | E1: Date of last paid | F1: Projects Name
A2: Arif Bangali | B2: 1200 | C2: 1000 | D2: =B2-C2 -> 200 | F2: pillows | G2: Partically Paid
A3: Arif Bangali | B3: 1400 | C3: 0 | D3: =B3-C3 -> 1400 | F3: loder/sapc
A4: Arif Bangali | B4: 1000 | C4: 0 | D4: =B4-C4 -> 1000 | F4: Modification of pillows | G4: Full Paid
A5: Massri | B5: 5500 | C5: 5500 | D5: =B5-C5 -> 0 | F5: rubber of pully/Modern Mills | G5: Full Paid
A6: Massri | B6: 600 | C6: 0 | D6: =B6-C6 -> 600 | F6: rubber of small pully/Modern Mills
A7: Yousri | B7: 2000 | C7: 0 | D7: =B7-C7 -> 2000 | F7: Maintenance of pully
A8: Arif Bangali | B8: 1000 | C8: 0 | D8: =B8-C8 -> 1000 | F8: Pully/Modern Mills | G8: Full Paid
A9: Shahbaz Mills | B9: 2600 | C9: 2000 | D9: =B9-C9 -> 600 | F9: For Prainsa work | G9: Partically Paid
A10: Yousri | B10: 2400 | C10: 0 | D10: =B10-C10 -> 2400 | F10: Binladin Engine
A11: Moeen Transport | B11: 700 | C11: 0 | D11: =B11-C11 -> 700 | F11: For Transport | G11: Full Paid
A12: Shoaib Yasin | B12: 10000 | C12: 0 | D12: =B12-C12 -> 10000 | F12: Old Accounts
A13: Abu Javid | B13: 5000 | C13: 0 | D13: =B13-C13 -> 5000 | F13: Hali Project
A14: Farhan Molvi | B14: 3500 | C14: 0 | D14: =B14-C14 -> 3500 | F14: Old Accounts
A15: Insaf Tech | B15: 800 | C15: 0 | D15: =B15-C15 -> 800 | F15: Old Accounts
A16: Seal Tick | B16: 1500 | C16: 0 | D16: =B16-C16 -> 1500 | F16: Old Accounts
A17: Yousaf | B17: 10000 | C17: 5000 | D17: =B17-C17 -> 5000 | F17: Old Accounts | G17: Partically Paid
A18: Khurram Millings | B18: 10000 | C18: 0 | D18: =B18-C18 -> 10000 | F18: Old Accounts
A19: Abdullah Khan | B19: 3000 | C19: 300 | D19: =B19-C19 -> 2700 | F19: Old Accounts
A20: Usman Generator | B20: 41272 | C20: 12000 | D20: =B20-C20 -> 29272 | F20: 15k old account, 6220 MBL company, 8475 old perkins+CAT+denmo+CAT Radiator+PTE+Rent, 5577 for Perkits 1300 2pc genset and one 100kW denmo+ 1000 for Madina work
A21: Raqib Radiator | B21: 1500 | C21: 0 | D21: =B21-C21 -> 1500 | F21: Old Accounts
A22: Naswar | B22: 1000 | C22: 0 | D22: =B22-C22 -> 1000 | F22: Old Accounts
A23: Mehmood Baksh | B23: 3500 | C23: 0 | D23: =B23-C23 -> 3500 | F23: Old Accounts
A24: Naeem | B24: 3500 | C24: 2000 | D24: =B24-C24 -> 1500 | F24: Old Accounts | G24: Partically Paid
A25: Yasri Shah | B25: 8000 | C25: 0 | D25: =B25-C25 -> 8000 | F25: Old Accounts
A26: Naziq/Pakistan | B26: 300 | C26: 300 | D26: =B26-C26 -> 0 | F26: Old Accounts | G26: Full Paid
A27: Tax | B27: 21000 | C27: 0 | D27: =B27-C27 -> 21000 | F27: Old Accounts
A28: Imran Mechanic | B28: 1000 | C28: 0 | D28: =B28-C28 -> 1000 | F28: Old Accounts
A29: Abbas | B29: 3000 | C29: 0 | D29: =B29-C29 -> 3000 | F29: Old Accounts
A30: Raqib Radiator | B30: 3300 | C30: 0 | D30: =B30-C30 -> 3300 | F30: Grader Radiator
A31: Raqib Radiator | B31: 900 | C31: 0 | D31: =B31-C31 -> 900 | F31: Genset Radiator
A32: Saleries | B32: 3000 | C32: 0 | D32: =B32-C32 -> 3000 | F32: Abdullah and chacha of March Month
D33: =B33-C33 -> 0
D34: =B34-C34 -> 0
D35: =B35-C35 -> 0
D36: =B36-C36 -> 0
D37: =B37-C37 -> 0
D38: =B38-C38 -> 0
D39: =B39-C39 -> 0
D40: =B40-C40 -> 0
D41: =B41-C41 -> 0
D42: =B42-C42 -> 0
D43: =B43-C43 -> 0
D44: =B44-C44 -> 0
... D200: =B200-C200 -> 0
