Workbook
Name CategoryList: #REF!

Sheet Transactions
A1: Date | B1: Description | C1: Type (IN/OUT) | D1: Amount (Excl. VAT) | E1: Account | F1: Category | G1: Project | H1: Material Item | I1: Qty | J1: Rate | K1: Party Name | L1: Party Type | M1: Invoice # | N1: Tax % | O1: Tax Amount | P1: Total Amount | Q1: Payment Status | R1: Notes
A2: 45965 | B2: chemicals | C2: OUT | D2: 220 | E2: Cash | F2: Material Purchase | G2: SS316 Pipeline Work | H2: Material/Tools | K2: TBD | L2: Supplier | N2: 15 | O2: =IF(OR(D2="", N2=""), "", ROUND(D2 * N2 / 100, 2)) | P2: =IF(D2="", "", D2 + O2) | Q2: Paid

Sheet Projects
A1: Project Name | B1: Client Name | C1: Contract Value (Excl. VAT) | D1: VAT 15% | E1: Contract Incl. VAT | F1: Required 50% Advance (Incl. VAT) | G1: Total Income | H1: Total Expense | I1: Net Profit / Loss | J1: Remaining Amount
A2: SS316 Pipeline Work | B2: Oud Lover Factory | C2: 4000 | D2: =IF(C2="","",ROUND(C2*0.15,2)) | E2: =IF(C2="","",C2+D2) | F2: =IF(E2="","",E2*0.5) | G2: =IF($A2="","", SUMIFS(Transactions!$P:$P, Transactions!$G:$G,$A2, Transactions!$C:$C,"IN", Transactions!$Q:$Q,"*Paid*")) | H2: =IF($A2="","", SUMIFS(Transactions!$P:$P, Transactions!$G:$G,$A2, Transactions!$C:$C,"OUT")) | I2: =IF(C2="","",C2-H2) | J2: =IF(E2="","",E2-G2)

Sheet Accounts_Summary
A1: Account Name | B1: Total IN | C1: Total OUT | D1: Balance
A2: Cash | B2: =SUMIFS(Transactions!$P:$P,Transactions!$C:$C,"IN",Transactions!$E:$E,$A2) | C2: =SUMIFS(Transactions!$P:$P,Transactions!$C:$C,"OUT",Transactions!$E:$E,$A2) | D2: =B2-C2 | E2: With VAT

Sheet Tax Report
A1: Month | B1: Year | C1: Total Sales (Excl. VAT) | D1: Output VAT 15% | E1: Total Purchases (Excl. VAT) | F1: Input VAT 15% | G1: Net VAT Payable
A2: 11 | B2: 2025 | C2: =IF(OR($A2="",$B2=""),"", SUMIFS(Transactions!$D:$D, Transactions!$C:$C,"IN", Transactions!$L:$L,"Client", Transactions!$Q:$Q,"*Paid*", Transactions!$A:$A,">="&DATE($B2,$A2,1), Transactions!$A:$A,"<"&EDATE(DATE($B2,$A2,1),1) ) ) | D2: =IF(OR($A2="",$B2=""),"", SUMIFS(Transactions!$O:$O, Transactions!$C:$C,"IN", Transactions!$L:$L,"Client", Transactions!$Q:$Q,"*Paid*", Transactions!$A:$A,">="&DATE($B2,$A2,1), Transactions!$A:$A,"<"&EDATE(DATE($B2,$A2,1),1) ) ) | E2: =SUMIFS( Transactions!$D:$D, Transactions!$C:$C,"OUT", Transactions!$E:$E,"Cash", Transactions!$A:$A,">=" & DATE($B2,$A2,1), Transactions!$A:$A,"<" & DATE($B2,$A2+1,1) ) | F2: =SUMIFS( Transactions!$O:$O, Transactions!$C:$C,"OUT", Transactions!$E:$E,"Cash", Transactions!$A:$A,">=" & DATE($B2,$A2,1), Transactions!$A:$A,"<" & DATE($B2,$A2+1,1) ) | G2: =IF(OR(D2="",F2=""),"",D2-F2)

Sheet Monthly_Report
A1: Month | B1: Year | C1: Total Income (Excl. VAT) | D1: Total Expense (Excl. VAT) | E1: Net Profit / Loss | F1: Material Expense | G1: Food Expense | H1: Fuel Expense | I1: Labour Expense | J1: Transport Expense | K1: Credit Sale
A2: 11 | B2: 2025 | C2: =SUMIFS( Transactions!$D:$D, Transactions!$C:$C,"IN", Transactions!$E:$E,"Cash", Transactions!$A:$A,">=" & DATE($B2,$A2,1), Transactions!$A:$A,"<" & EOMONTH(DATE($B2,$A2,1),0)+1 ) | D2: =SUMIFS( Transactions!$D:$D, Transactions!$C:$C,"OUT", Transactions!$E:$E,"Cash", Transactions!$A:$A,">="&DATE($B2,$A2,1), Transactions!$A:$A,"<"&DATE($B2,$A2+1,1) ) | E2: =C2-D2 | F2: =SUMIFS( Transactions!$D:$D, Transactions!$C:$C,"OUT", Transactions!$E:$E,"Cash", Transactions!$F:$F,"Material Purchase", Transactions!$A:$A,">="&DATE($B2,$A2,1), Transactions!$A:$A,"<"&DATE($B2,$A2+1,1) ) | G2: =SUMIFS( Transactions!$D:$D, Transactions!$C:$C,"OUT", Transactions!$E:$E,"Cash", Transactions!$F:$F,"Food Expense", Transactions!$A:$A,">="&DATE($B2,$A2,1), Transactions!$A:$A,"<"&DATE($B2,$A2+1,1) ) | H2: =SUMIFS( Transactions!$D:$D, Transactions!$C:$C,"OUT", Transactions!$E:$E,"Cash", Transactions!$F:$F,"Fuel Expense", Transactions!$A:$A,">="&DATE($B2,$A2,1), Transactions!$A:$A,"<"&DATE($B2,$A2+1,1) ) | I2: =SUMIFS( Transactions!$D:$D, Transactions!$C:$C,"OUT", Transactions!$E:$E,"Cash", Transactions!$F:$F,"Labour Expense", Transactions!$A:$A,">="&DATE($B2,$A2,1), Transactions!$A:$A,"<"&DATE($B2,$A2+1,1) ) | J2: =SUMIFS( Transactions!$D:$D, Transactions!$C:$C,"OUT", Transactions!$E:$E,"Cash", Transactions!$F:$F,"Transport Expense", Transactions!$A:$A,">="&DATE($B2,$A2,1), Transactions!$A:$A,"<"&DATE($B2,$A2+1,1) ) | K2: =SUMIFS( Transactions!$D:$D, Transactions!$C:$C,"IN", Transactions!$E:$E,"Accounts Receivable", Transactions!$A:$A,">=" & DATE($B2,$A2,1), Transactions!$A:$A,"<" & EOMONTH(DATE($B2,$A2,1),0)+1 )

Sheet Employees
A1: Employee Name | B1: Type (Monthly/Daily) | C1: Monthly Salary | D1: Daily Rate | E1: Days Worked (This Month) | F1: Salary Due This Month | G1: Total Salary Paid This Month | H1: Pending Salary This Month | I1: Total Advance Taken | J1: Total Advance Adjusted | K1: Advance Balance | L1: Previous Pending Salary | M1: Total Pending Salary(All Months) | N1: Note
A2: Shoaib Umar | B2: Monthly | C2: 1800 | E2: 19 | F2: =IFERROR( IF(B2="Monthly", C2, IF(B2="Daily", D2*E2, IF(B2="Weekly", C2, 0 ) ) ), 0) | G2: 1800 | H2: =IFERROR(IF(F2="",0,F2-G2),0) | K2: =IFERROR(IF(I2="",0,I2-J2),0) | L2: 1800 | M2: =IFERROR(H2+L2,0) | N2: Running Month 15-11-2025 to 15-12-2025

Sheet Dashboard
A1: Metric | B1: Value
A2: Total Cash Balance | B2: =Accounts_Summary!D2

Sheet Old Accounts Payable
A1: Suppliars Names | B1: Total payable | C1: Total paid | D1: Total Remain after Paid | E1: Date of last paid | F1: Projects Name
A2: Arif Bangali | B2: 1200 | C2: 1000 | D2: =B2-C2 | F2: pillows | G2: Partically Paid
